{
  "metadata": {
    "last_updated": "2026-05-20",
    "usd_brl_rate": 5.87,
    "version": "1.0"
  },
  "positions": [
    {
      "id": 1,
      "data_aplicacao": "03/06/2025",
      "corretora": "XP",
      "titulo": "CRI MRL - SET/2026",
      "emissor": "MRL",
      "taxa": "IPC-A +10,42%",
      "vencimento": "15/09/2026",
      "classe": "RENDA FIXA",
      "tipo": "IPCA+",
      "ticker": "",
      "moeda": "BRL",
      "custo_brl": 49220.7,
      "atual_brl": 53936.3,
      "status": "ativo"
    },
    {
      "id": 2,
      "data_aplicacao": "22/01/2025",
      "corretora": "XP",
      "titulo": "CRI BRASOL - FEV/2036",
      "emissor": "BRASOL",
      "taxa": "IPC-A +11,94%",
      "vencimento": "28/02/2036",
      "classe": "RENDA FIXA",
      "tipo": "IPCA+",
      "ticker": "",
      "moeda": "BRL",
      "custo_brl": 48781.33,
      "atual_brl": 52424.24,
      "status": "ativo"
    },
    {
      "id": 3,
      "data_aplicacao": "06/01/2026",
      "corretora": "XP",
      "titulo": "CRA JSL - MAI/2031",
      "emissor": "JSL",
      "taxa": "IPC-A +11,70%",
      "vencimento": "16/05/2031",
      "classe": "RENDA FIXA",
      "tipo": "IPCA+",
      "ticker": "",
      "moeda": "BRL",
      "custo_brl": 49371.33,
      "atual_brl": 51648.76,
      "status": "ativo"
    },
    {
      "id": 4,
      "data_aplicacao": "23/04/2025",
      "corretora": "XP",
      "titulo": "CRA USINA SÃO FRANCISCO - JUL/2028",
      "emissor": "USINA SÃO FRANCISCO",
      "taxa": "IPC-A +10,58%",
      "vencimento": "17/07/2028",
      "classe": "RENDA FIXA",
      "tipo": "IPCA+",
      "ticker": "",
      "moeda": "BRL",
      "custo_brl": 33845.62,
      "atual_brl": 38221.73,
      "status": "ativo"
    },
    {
      "id": 5,
      "data_aplicacao": "03/12/2025",
      "corretora": "XP",
      "titulo": "CRA VAMOS - JUN/2027",
      "emissor": "VAMOS",
      "taxa": "IPC-A +12,70%",
      "vencimento": "15/06/2027",
      "classe": "RENDA FIXA",
      "tipo": "IPCA+",
      "ticker": "",
      "moeda": "BRL",
      "custo_brl": 33015.26,
      "atual_brl": 35819.15,
      "status": "ativo"
    },
    {
      "id": 6,
      "data_aplicacao": "18/11/2025",
      "corretora": "XP",
      "titulo": "CRA ADECOAGRO - NOV/2027",
      "emissor": "ADECOAGRO",
      "taxa": "IPC-A +12,90%",
      "vencimento": "17/11/2027",
      "classe": "RENDA FIXA",
      "tipo": "IPCA+",
      "ticker": "",
      "moeda": "BRL",
      "custo_brl": 32311.61,
      "atual_brl": 35351.09,
      "status": "ativo"
    },
    {
      "id": 7,
      "data_aplicacao": "23/09/2024",
      "corretora": "XP",
      "titulo": "CRA ADUBOS ARAGUAIA - JUL/2027",
      "emissor": "ADUBOS ARAGUAIA",
      "taxa": "IPC-A +9,25%",
      "vencimento": "15/07/2027",
      "classe": "RENDA FIXA",
      "tipo": "IPCA+",
      "ticker": "",
      "moeda": "BRL",
      "custo_brl": 30762.39,
      "atual_brl": 34948.09,
      "status": "ativo"
    },
    {
      "id": 8,
      "data_aplicacao": "23/09/2024",
      "corretora": "XP",
      "titulo": "CRA OLFAR - MAR/2030",
      "emissor": "OLFAR",
      "taxa": "IPC-A +8,90%",
      "vencimento": "15/03/2030",
      "classe": "RENDA FIXA",
      "tipo": "IPCA+",
      "ticker": "",
      "moeda": "BRL",
      "custo_brl": 31814.62,
      "atual_brl": 34655.32,
      "status": "ativo"
    },
    {
      "id": 9,
      "data_aplicacao": "27/01/2026",
      "corretora": "XP",
      "titulo": "CRA ADECOAGRO - NOV/2027 (2)",
      "emissor": "ADECOAGRO",
      "taxa": "IPC-A +12,55%",
      "vencimento": "17/11/2027",
      "classe": "RENDA FIXA",
      "tipo": "IPCA+",
      "ticker": "",
      "moeda": "BRL",
      "custo_brl": 32103.21,
      "atual_brl": 34092.49,
      "status": "ativo"
    },
    {
      "id": 10,
      "data_aplicacao": "24/11/2025",
      "corretora": "XP",
      "titulo": "CRI MOVIDA - JUN/2028",
      "emissor": "MOVIDA",
      "taxa": "IPC-A +12,35%",
      "vencimento": "16/06/2028",
      "classe": "RENDA FIXA",
      "tipo": "IPCA+",
      "ticker": "",
      "moeda": "BRL",
      "custo_brl": 31501.62,
      "atual_brl": 33995.12,
      "status": "ativo"
    },
    {
      "id": 11,
      "data_aplicacao": "15/01/2026",
      "corretora": "XP",
      "titulo": "CRI HAPVIDA - DEZ/2031",
      "emissor": "HAPVIDA",
      "taxa": "IPC-A +10,50%",
      "vencimento": "15/12/2031",
      "classe": "RENDA FIXA",
      "tipo": "IPCA+",
      "ticker": "",
      "moeda": "BRL",
      "custo_brl": 31920.6,
      "atual_brl": 33863.75,
      "status": "ativo"
    },
    {
      "id": 12,
      "data_aplicacao": "09/09/2025",
      "corretora": "XP",
      "titulo": "CRI CONSTRUTORA TENDA - ABR/2028",
      "emissor": "CONSTRUTORA TENDA",
      "taxa": "IPC-A +12,24%",
      "vencimento": "17/04/2028",
      "classe": "RENDA FIXA",
      "tipo": "IPCA+",
      "ticker": "",
      "moeda": "BRL",
      "custo_brl": 30536.51,
      "atual_brl": 33621.03,
      "status": "ativo"
    },
    {
      "id": 13,
      "data_aplicacao": "23/09/2024",
      "corretora": "XP",
      "titulo": "CRA FAZENDÃO - NOV/2030",
      "emissor": "FAZENDÃO",
      "taxa": "IPC-A +9,55%",
      "vencimento": "18/11/2030",
      "classe": "RENDA FIXA",
      "tipo": "IPCA+",
      "ticker": "",
      "moeda": "BRL",
      "custo_brl": 30530.82,
      "atual_brl": 33514.4,
      "status": "ativo"
    },
    {
      "id": 14,
      "data_aplicacao": "21/10/2025",
      "corretora": "XP",
      "titulo": "CRA OBA HORTIFRUTI - DEZ/2027",
      "emissor": "OBA HORTIFRUTI",
      "taxa": "IPC-A +11,85%",
      "vencimento": "15/12/2027",
      "classe": "RENDA FIXA",
      "tipo": "IPCA+",
      "ticker": "",
      "moeda": "BRL",
      "custo_brl": 30125.85,
      "atual_brl": 32495.82,
      "status": "ativo"
    },
    {
      "id": 15,
      "data_aplicacao": "05/03/2026",
      "corretora": "XP",
      "titulo": "CRI GRUPO JOSÉ ALVES - JUN/2029",
      "emissor": "GRUPO JOSÉ ALVES",
      "taxa": "IPC-A +10,75%",
      "vencimento": "15/06/2029",
      "classe": "RENDA FIXA",
      "tipo": "IPCA+",
      "ticker": "",
      "moeda": "BRL",
      "custo_brl": 29414.67,
      "atual_brl": 30192.82,
      "status": "ativo"
    },
    {
      "id": 16,
      "data_aplicacao": "16/10/2024",
      "corretora": "XP",
      "titulo": "CRA AGRO QUARTZO - SET/2030",
      "emissor": "AGRO QUARTZO",
      "taxa": "IPC-A +9,75%",
      "vencimento": "16/09/2030",
      "classe": "RENDA FIXA",
      "tipo": "IPCA+",
      "ticker": "",
      "moeda": "BRL",
      "custo_brl": 25541.28,
      "atual_brl": 28657.14,
      "status": "ativo"
    },
    {
      "id": 17,
      "data_aplicacao": "16/03/2026",
      "corretora": "XP",
      "titulo": "DEB TEREOS - JUN/2027",
      "emissor": "TEREOS",
      "taxa": "IPC-A +10,00%",
      "vencimento": "15/06/2027",
      "classe": "RENDA FIXA",
      "tipo": "IPCA+",
      "ticker": "",
      "moeda": "BRL",
      "custo_brl": 26098.36,
      "atual_brl": 26952.45,
      "status": "ativo"
    },
    {
      "id": 18,
      "data_aplicacao": "06/02/2026",
      "corretora": "XP",
      "titulo": "DEB TEREOS - JUN/2027 (2)",
      "emissor": "TEREOS",
      "taxa": "IPC-A +10,15%",
      "vencimento": "15/06/2027",
      "classe": "RENDA FIXA",
      "tipo": "IPCA+",
      "ticker": "",
      "moeda": "BRL",
      "custo_brl": 24777.24,
      "atual_brl": 26034.95,
      "status": "ativo"
    },
    {
      "id": 19,
      "data_aplicacao": "03/11/2025",
      "corretora": "XP",
      "titulo": "CRA OBA HORTIFRUTI - DEZ/2027 (2)",
      "emissor": "OBA HORTIFRUTI",
      "taxa": "IPC-A +11,80%",
      "vencimento": "15/12/2027",
      "classe": "RENDA FIXA",
      "tipo": "IPCA+",
      "ticker": "",
      "moeda": "BRL",
      "custo_brl": 22787.05,
      "atual_brl": 24505.37,
      "status": "ativo"
    },
    {
      "id": 20,
      "data_aplicacao": "06/11/2024",
      "corretora": "XP",
      "titulo": "CRI SAGA MALLS - SET/2034",
      "emissor": "SAGA MALLS",
      "taxa": "IPC-A +9,85%",
      "vencimento": "29/09/2034",
      "classe": "RENDA FIXA",
      "tipo": "IPCA+",
      "ticker": "",
      "moeda": "BRL",
      "custo_brl": 22237.26,
      "atual_brl": 24493.65,
      "status": "ativo"
    },
    {
      "id": 21,
      "data_aplicacao": "12/11/2024",
      "corretora": "XP",
      "titulo": "CRA BARTIRA - ABR/2032",
      "emissor": "BARTIRA",
      "taxa": "IPC-A +8,30%",
      "vencimento": "05/04/2032",
      "classe": "RENDA FIXA",
      "tipo": "IPCA+",
      "ticker": "",
      "moeda": "BRL",
      "custo_brl": 21666.29,
      "atual_brl": 24383.14,
      "status": "ativo"
    },
    {
      "id": 22,
      "data_aplicacao": "01/04/2026",
      "corretora": "XP",
      "titulo": "CRI TRISUL - FEV/2030",
      "emissor": "TRISUL",
      "taxa": "IPC-A +9,93%",
      "vencimento": "25/02/2030",
      "classe": "RENDA FIXA",
      "tipo": "IPCA+",
      "ticker": "",
      "moeda": "BRL",
      "custo_brl": 23354.69,
      "atual_brl": 23811.47,
      "status": "ativo"
    },
    {
      "id": 23,
      "data_aplicacao": "29/08/2024",
      "corretora": "XP",
      "titulo": "CRA FS BIOENERGIA - FEV/2029",
      "emissor": "FS BIOENERGIA",
      "taxa": "IPC-A +8,55%",
      "vencimento": "15/02/2029",
      "classe": "RENDA FIXA",
      "tipo": "IPCA+",
      "ticker": "",
      "moeda": "BRL",
      "custo_brl": 20465.45,
      "atual_brl": 23073.43,
      "status": "ativo"
    },
    {
      "id": 24,
      "data_aplicacao": "29/08/2024",
      "corretora": "XP",
      "titulo": "CRA FS BIOENERGIA - FEV/2029 (2)",
      "emissor": "FS BIOENERGIA",
      "taxa": "IPC-A +8,55%",
      "vencimento": "15/02/2029",
      "classe": "RENDA FIXA",
      "tipo": "IPCA+",
      "ticker": "",
      "moeda": "BRL",
      "custo_brl": 20465.45,
      "atual_brl": 23073.43,
      "status": "ativo"
    },
    {
      "id": 25,
      "data_aplicacao": "18/02/2026",
      "corretora": "XP",
      "titulo": "DEB CSN MINERACAO - JUL/2031",
      "emissor": "CSN MINERACAO",
      "taxa": "IPC-A +12,35%",
      "vencimento": "15/07/2031",
      "classe": "RENDA FIXA",
      "tipo": "IPCA+",
      "ticker": "",
      "moeda": "BRL",
      "custo_brl": 21383.6,
      "atual_brl": 22504.73,
      "status": "ativo"
    },
    {
      "id": 26,
      "data_aplicacao": "11/02/2025",
      "corretora": "XP",
      "titulo": "CRI CONX - JUL/2027",
      "emissor": "CONX",
      "taxa": "IPC-A +10,95%",
      "vencimento": "15/07/2027",
      "classe": "RENDA FIXA",
      "tipo": "IPCA+",
      "ticker": "",
      "moeda": "BRL",
      "custo_brl": 19242.3,
      "atual_brl": 22242.57,
      "status": "ativo"
    },
    {
      "id": 27,
      "data_aplicacao": "24/10/2024",
      "corretora": "XP",
      "titulo": "CRA NARDINI - ABR/2028",
      "emissor": "NARDINI",
      "taxa": "IPC-A +8,45%",
      "vencimento": "17/04/2028",
      "classe": "RENDA FIXA",
      "tipo": "IPCA+",
      "ticker": "",
      "moeda": "BRL",
      "custo_brl": 19098.5,
      "atual_brl": 22103.73,
      "status": "ativo"
    },
    {
      "id": 28,
      "data_aplicacao": "17/09/2024",
      "corretora": "XP",
      "titulo": "CRI SOLAR GRID - DEZ/2038",
      "emissor": "SOLAR GRID",
      "taxa": "IPC-A +9,40%",
      "vencimento": "15/12/2038",
      "classe": "RENDA FIXA",
      "tipo": "IPCA+",
      "ticker": "",
      "moeda": "BRL",
      "custo_brl": 19079.55,
      "atual_brl": 21148.87,
      "status": "ativo"
    },
    {
      "id": 29,
      "data_aplicacao": "26/11/2025",
      "corretora": "XP",
      "titulo": "CRI BELENUS - ABR/2029",
      "emissor": "BELENUS",
      "taxa": "IPC-A +11,95%",
      "vencimento": "18/04/2029",
      "classe": "RENDA FIXA",
      "tipo": "IPCA+",
      "ticker": "",
      "moeda": "BRL",
      "custo_brl": 19878.46,
      "atual_brl": 20910.7,
      "status": "ativo"
    },
    {
      "id": 30,
      "data_aplicacao": "06/01/2026",
      "corretora": "XP",
      "titulo": "CDCA VAMOS - SET/2031",
      "emissor": "VAMOS",
      "taxa": "IPC-A +11,90%",
      "vencimento": "15/09/2031",
      "classe": "RENDA FIXA",
      "tipo": "IPCA+",
      "ticker": "",
      "moeda": "BRL",
      "custo_brl": 19735.33,
      "atual_brl": 20776.3,
      "status": "ativo"
    },
    {
      "id": 31,
      "data_aplicacao": "03/11/2025",
      "corretora": "XP",
      "titulo": "CRI AUTOMOB - ABR/2030",
      "emissor": "AUTOMOB",
      "taxa": "IPC-A +11,75%",
      "vencimento": "15/04/2030",
      "classe": "RENDA FIXA",
      "tipo": "IPCA+",
      "ticker": "",
      "moeda": "BRL",
      "custo_brl": 19692.29,
      "atual_brl": 20736.75,
      "status": "ativo"
    },
    {
      "id": 32,
      "data_aplicacao": "18/12/2025",
      "corretora": "XP",
      "titulo": "CRI BELENUS - ABR/2029 (2)",
      "emissor": "BELENUS",
      "taxa": "IPC-A +12,15%",
      "vencimento": "18/04/2029",
      "classe": "RENDA FIXA",
      "tipo": "IPCA+",
      "ticker": "",
      "moeda": "BRL",
      "custo_brl": 18574.46,
      "atual_brl": 19467.42,
      "status": "ativo"
    },
    {
      "id": 33,
      "data_aplicacao": "13/10/2025",
      "corretora": "XP",
      "titulo": "CRA TIROLEZ - JAN/2028",
      "emissor": "TIROLEZ",
      "taxa": "IPC-A +11,20%",
      "vencimento": "17/01/2028",
      "classe": "RENDA FIXA",
      "tipo": "IPCA+",
      "ticker": "",
      "moeda": "BRL",
      "custo_brl": 17714.44,
      "atual_brl": 19328.94,
      "status": "ativo"
    },
    {
      "id": 34,
      "data_aplicacao": "05/02/2025",
      "corretora": "XP",
      "titulo": "CRI URBA - DEZ/2039",
      "emissor": "URBA (GRUPO DA MRV)",
      "taxa": "IPC-A +10,50%",
      "vencimento": "26/12/2039",
      "classe": "RENDA FIXA",
      "tipo": "IPCA+",
      "ticker": "",
      "moeda": "BRL",
      "custo_brl": 17549.0,
      "atual_brl": 18886.29,
      "status": "ativo"
    },
    {
      "id": 35,
      "data_aplicacao": "01/10/2024",
      "corretora": "XP",
      "titulo": "CRA PLANAGRI - JUN/2028",
      "emissor": "PLANAGRI",
      "taxa": "IPC-A +8,75%",
      "vencimento": "16/06/2028",
      "classe": "RENDA FIXA",
      "tipo": "IPCA+",
      "ticker": "",
      "moeda": "BRL",
      "custo_brl": 15157.37,
      "atual_brl": 18504.68,
      "status": "ativo"
    },
    {
      "id": 36,
      "data_aplicacao": "06/11/2024",
      "corretora": "XP",
      "titulo": "CRI CONSTRUTORA TENDA - ABR/2028 (2)",
      "emissor": "CONSTRUTORA TENDA",
      "taxa": "IPC-A +9,45%",
      "vencimento": "17/04/2028",
      "classe": "RENDA FIXA",
      "tipo": "IPCA+",
      "ticker": "",
      "moeda": "BRL",
      "custo_brl": 15354.79,
      "atual_brl": 18255.31,
      "status": "ativo"
    },
    {
      "id": 37,
      "data_aplicacao": "01/04/2026",
      "corretora": "XP",
      "titulo": "CRI DURLI COUROS - FEV/2027",
      "emissor": "DURLI COUROS",
      "taxa": "IPC-A +11,39%",
      "vencimento": "15/02/2027",
      "classe": "RENDA FIXA",
      "tipo": "IPCA+",
      "ticker": "",
      "moeda": "BRL",
      "custo_brl": 17686.18,
      "atual_brl": 18075.35,
      "status": "ativo"
    },
    {
      "id": 38,
      "data_aplicacao": "10/09/2024",
      "corretora": "XP",
      "titulo": "CRI DELTA - MAI/2032",
      "emissor": "DELTA",
      "taxa": "IPC-A +8,60%",
      "vencimento": "15/05/2032",
      "classe": "RENDA FIXA",
      "tipo": "IPCA+",
      "ticker": "",
      "moeda": "BRL",
      "custo_brl": 16433.1,
      "atual_brl": 18067.23,
      "status": "ativo"
    },
    {
      "id": 39,
      "data_aplicacao": "17/09/2024",
      "corretora": "XP",
      "titulo": "CRA FS FLORESTAL - JUN/2032",
      "emissor": "FS FLORESTAL",
      "taxa": "IPC-A +8,90%",
      "vencimento": "15/06/2032",
      "classe": "RENDA FIXA",
      "tipo": "IPCA+",
      "ticker": "",
      "moeda": "BRL",
      "custo_brl": 16335.81,
      "atual_brl": 17777.62,
      "status": "ativo"
    },
    {
      "id": 40,
      "data_aplicacao": "11/09/2024",
      "corretora": "XP",
      "titulo": "CRI DASA - OUT/2029",
      "emissor": "DASA",
      "taxa": "IPC-A +8,45%",
      "vencimento": "15/10/2029",
      "classe": "RENDA FIXA",
      "tipo": "IPCA+",
      "ticker": "",
      "moeda": "BRL",
      "custo_brl": 15131.03,
      "atual_brl": 16978.9,
      "status": "ativo"
    },
    {
      "id": 41,
      "data_aplicacao": "30/09/2025",
      "corretora": "XP",
      "titulo": "CRA AGROINSUMOS - MAI/2030",
      "emissor": "AGROINSUMOS",
      "taxa": "IPC-A +12,95%",
      "vencimento": "15/05/2030",
      "classe": "RENDA FIXA",
      "tipo": "IPCA+",
      "ticker": "",
      "moeda": "BRL",
      "custo_brl": 15932.86,
      "atual_brl": 16857.15,
      "status": "ativo"
    },
    {
      "id": 42,
      "data_aplicacao": "06/09/2024",
      "corretora": "XP",
      "titulo": "CRA FS FLORESTAL - JUN/2032 (2)",
      "emissor": "FS FLORESTAL",
      "taxa": "IPC-A +8,70%",
      "vencimento": "15/06/2032",
      "classe": "RENDA FIXA",
      "tipo": "IPCA+",
      "ticker": "",
      "moeda": "BRL",
      "custo_brl": 15467.64,
      "atual_brl": 16801.76,
      "status": "ativo"
    },
    {
      "id": 43,
      "data_aplicacao": "29/08/2025",
      "corretora": "XP",
      "titulo": "CRA RAIZEN - AGO/2032",
      "emissor": "RAIZEN",
      "taxa": "IPC-A +9,95%",
      "vencimento": "16/08/2032",
      "classe": "RENDA FIXA",
      "tipo": "IPCA+",
      "ticker": "",
      "moeda": "BRL",
      "custo_brl": 32574.83,
      "atual_brl": 15983.25,
      "status": "ativo"
    },
    {
      "id": 44,
      "data_aplicacao": "11/09/2024",
      "corretora": "XP",
      "titulo": "DEB VERO S.A. - MAR/2031",
      "emissor": "VERO S.A.",
      "taxa": "IPC-A +8,05%",
      "vencimento": "15/03/2031",
      "classe": "RENDA FIXA",
      "tipo": "IPCA+",
      "ticker": "",
      "moeda": "BRL",
      "custo_brl": 14425.07,
      "atual_brl": 15911.61,
      "status": "ativo"
    },
    {
      "id": 45,
      "data_aplicacao": "01/07/2025",
      "corretora": "XP",
      "titulo": "CRA FAZENDÃO - NOV/2030 (2)",
      "emissor": "FAZENDÃO",
      "taxa": "IPC-A +12,60%",
      "vencimento": "18/11/2030",
      "classe": "RENDA FIXA",
      "tipo": "IPCA+",
      "ticker": "",
      "moeda": "BRL",
      "custo_brl": 14832.25,
      "atual_brl": 15802.31,
      "status": "ativo"
    },
    {
      "id": 46,
      "data_aplicacao": "16/09/2024",
      "corretora": "XP",
      "titulo": "CRA AGROINSUMOS - MAI/2030 (2)",
      "emissor": "AGROINSUMOS",
      "taxa": "IPC-A +9,95%",
      "vencimento": "15/05/2030",
      "classe": "RENDA FIXA",
      "tipo": "IPCA+",
      "ticker": "",
      "moeda": "BRL",
      "custo_brl": 13883.44,
      "atual_brl": 15554.15,
      "status": "ativo"
    },
    {
      "id": 47,
      "data_aplicacao": "07/10/2025",
      "corretora": "XP",
      "titulo": "CRA PIRACANJUBA - OUT/2028",
      "emissor": "PIRACANJUBA",
      "taxa": "IPC-A +10,20%",
      "vencimento": "16/10/2028",
      "classe": "RENDA FIXA",
      "tipo": "IPCA+",
      "ticker": "",
      "moeda": "BRL",
      "custo_brl": 14350.26,
      "atual_brl": 15294.44,
      "status": "ativo"
    },
    {
      "id": 48,
      "data_aplicacao": "20/03/2025",
      "corretora": "XP",
      "titulo": "CRI GAPS MAQCAMPO - MAI/2032",
      "emissor": "GAPS",
      "taxa": "IPC-A +9,95%",
      "vencimento": "17/05/2032",
      "classe": "RENDA FIXA",
      "tipo": "IPCA+",
      "ticker": "",
      "moeda": "BRL",
      "custo_brl": 14043.78,
      "atual_brl": 15180.72,
      "status": "ativo"
    },
    {
      "id": 49,
      "data_aplicacao": "04/10/2024",
      "corretora": "XP",
      "titulo": "CRA JF CITRUS - OUT/2027",
      "emissor": "JF CITRUS",
      "taxa": "IPC-A +8,55%",
      "vencimento": "15/10/2027",
      "classe": "RENDA FIXA",
      "tipo": "IPCA+",
      "ticker": "",
      "moeda": "BRL",
      "custo_brl": 12898.92,
      "atual_brl": 14935.02,
      "status": "ativo"
    },
    {
      "id": 50,
      "data_aplicacao": "23/10/2024",
      "corretora": "XP",
      "titulo": "DEB IGUA SANEAMENTO - JUL/2034",
      "emissor": "IGUA SANEAMENTO",
      "taxa": "IPC-A +8,05%",
      "vencimento": "15/07/2034",
      "classe": "RENDA FIXA",
      "tipo": "IPCA+",
      "ticker": "",
      "moeda": "BRL",
      "custo_brl": 13099.0,
      "atual_brl": 14909.92,
      "status": "ativo"
    },
    {
      "id": 51,
      "data_aplicacao": "16/03/2026",
      "corretora": "XP",
      "titulo": "CRA JF CITRUS - MAR/2029",
      "emissor": "JF CITRUS",
      "taxa": "IPC-A +10,45%",
      "vencimento": "15/03/2029",
      "classe": "RENDA FIXA",
      "tipo": "IPCA+",
      "ticker": "",
      "moeda": "BRL",
      "custo_brl": 14336.93,
      "atual_brl": 14634.93,
      "status": "ativo"
    },
    {
      "id": 52,
      "data_aplicacao": "03/06/2025",
      "corretora": "XP",
      "titulo": "CRI MRV FLEX - AGO/2035",
      "emissor": "MRV FLEX",
      "taxa": "IPC-A +10,15%",
      "vencimento": "20/08/2035",
      "classe": "RENDA FIXA",
      "tipo": "IPCA+",
      "ticker": "",
      "moeda": "BRL",
      "custo_brl": 12468.91,
      "atual_brl": 13833.95,
      "status": "ativo"
    },
    {
      "id": 53,
      "data_aplicacao": "28/08/2025",
      "corretora": "XP",
      "titulo": "CRA RAIZEN - OUT/2033",
      "emissor": "RAIZEN",
      "taxa": "IPC-A +10,10%",
      "vencimento": "17/10/2033",
      "classe": "RENDA FIXA",
      "tipo": "IPCA+",
      "ticker": "",
      "moeda": "BRL",
      "custo_brl": 26171.98,
      "atual_brl": 13647.21,
      "status": "ativo"
    },
    {
      "id": 54,
      "data_aplicacao": "30/08/2024",
      "corretora": "XP",
      "titulo": "CRI BELENUS - ABR/2029 (3)",
      "emissor": "BELENUS",
      "taxa": "IPC-A +9,35%",
      "vencimento": "18/04/2029",
      "classe": "RENDA FIXA",
      "tipo": "IPCA+",
      "ticker": "",
      "moeda": "BRL",
      "custo_brl": 11258.13,
      "atual_brl": 12973.36,
      "status": "ativo"
    },
    {
      "id": 55,
      "data_aplicacao": "14/05/2025",
      "corretora": "XP",
      "titulo": "CRI SOLAR GRID - DEZ/2038 (2)",
      "emissor": "SOLAR GRID",
      "taxa": "IPC-A +10,50%",
      "vencimento": "15/12/2038",
      "classe": "RENDA FIXA",
      "tipo": "IPCA+",
      "ticker": "",
      "moeda": "BRL",
      "custo_brl": 12088.03,
      "atual_brl": 12811.06,
      "status": "ativo"
    },
    {
      "id": 56,
      "data_aplicacao": "25/09/2024",
      "corretora": "XP",
      "titulo": "CRI BELENUS - ABR/2029 (4)",
      "emissor": "BELENUS",
      "taxa": "IPC-A +9,20%",
      "vencimento": "18/04/2029",
      "classe": "RENDA FIXA",
      "tipo": "IPCA+",
      "ticker": "",
      "moeda": "BRL",
      "custo_brl": 10085.36,
      "atual_brl": 11554.58,
      "status": "ativo"
    },
    {
      "id": 57,
      "data_aplicacao": "17/09/2024",
      "corretora": "XP",
      "titulo": "CRI DELTA - MAI/2032 (2)",
      "emissor": "DELTA",
      "taxa": "IPC-A +8,70%",
      "vencimento": "15/05/2032",
      "classe": "RENDA FIXA",
      "tipo": "IPCA+",
      "ticker": "",
      "moeda": "BRL",
      "custo_brl": 10342.89,
      "atual_brl": 11383.87,
      "status": "ativo"
    },
    {
      "id": 58,
      "data_aplicacao": "06/01/2025",
      "corretora": "XP",
      "titulo": "CRA FS FLORESTAL - JUN/2032 (3)",
      "emissor": "FS FLORESTAL",
      "taxa": "IPC-A +11,25%",
      "vencimento": "15/06/2032",
      "classe": "RENDA FIXA",
      "tipo": "IPCA+",
      "ticker": "",
      "moeda": "BRL",
      "custo_brl": 10233.46,
      "atual_brl": 11135.92,
      "status": "ativo"
    },
    {
      "id": 59,
      "data_aplicacao": "06/01/2025",
      "corretora": "XP",
      "titulo": "CRA ADUBOS ARAGUAIA - JUL/2027 (2)",
      "emissor": "ADUBOS ARAGUAIA",
      "taxa": "IPC-A +11,00%",
      "vencimento": "15/07/2027",
      "classe": "RENDA FIXA",
      "tipo": "IPCA+",
      "ticker": "",
      "moeda": "BRL",
      "custo_brl": 9442.63,
      "atual_brl": 10739.15,
      "status": "ativo"
    },
    {
      "id": 60,
      "data_aplicacao": "21/10/2024",
      "corretora": "XP",
      "titulo": "CRI DURLI COUROS - FEV/2027 (2)",
      "emissor": "DURLI COUROS",
      "taxa": "IPC-A +8,10%",
      "vencimento": "15/02/2027",
      "classe": "RENDA FIXA",
      "tipo": "IPCA+",
      "ticker": "",
      "moeda": "BRL",
      "custo_brl": 7971.34,
      "atual_brl": 9680.34,
      "status": "ativo"
    },
    {
      "id": 61,
      "data_aplicacao": "10/09/2024",
      "corretora": "XP",
      "titulo": "CRI SOLAR GRID - DEZ/2038 (3)",
      "emissor": "SOLAR GRID",
      "taxa": "IPC-A +9,30%",
      "vencimento": "15/12/2038",
      "classe": "RENDA FIXA",
      "tipo": "IPCA+",
      "ticker": "",
      "moeda": "BRL",
      "custo_brl": 8717.04,
      "atual_brl": 9657.08,
      "status": "ativo"
    },
    {
      "id": 62,
      "data_aplicacao": "06/09/2024",
      "corretora": "XP",
      "titulo": "CRI MRV FLEX - MAR/2033",
      "emissor": "MRV FLEX",
      "taxa": "IPC-A +8,35%",
      "vencimento": "15/03/2033",
      "classe": "RENDA FIXA",
      "tipo": "IPCA+",
      "ticker": "",
      "moeda": "BRL",
      "custo_brl": 8499.7,
      "atual_brl": 9639.04,
      "status": "ativo"
    },
    {
      "id": 63,
      "data_aplicacao": "19/09/2024",
      "corretora": "XP",
      "titulo": "CRA PRIME AGRO - JUN/2028",
      "emissor": "PRIME AGRO",
      "taxa": "IPC-A +9,30%",
      "vencimento": "20/06/2028",
      "classe": "RENDA FIXA",
      "tipo": "IPCA+",
      "ticker": "",
      "moeda": "BRL",
      "custo_brl": 7240.91,
      "atual_brl": 8484.81,
      "status": "ativo"
    },
    {
      "id": 64,
      "data_aplicacao": "17/06/2025",
      "corretora": "XP",
      "titulo": "CRA AGROINSUMOS - MAI/2030 (3)",
      "emissor": "AGROINSUMOS",
      "taxa": "IPC-A +12,90%",
      "vencimento": "15/05/2030",
      "classe": "RENDA FIXA",
      "tipo": "IPCA+",
      "ticker": "",
      "moeda": "BRL",
      "custo_brl": 7846.27,
      "atual_brl": 8435.88,
      "status": "ativo"
    },
    {
      "id": 65,
      "data_aplicacao": "23/02/2026",
      "corretora": "XP",
      "titulo": "CRA GRUPO JOSÉ ALVES - MAI/2031",
      "emissor": "GRUPO JOSÉ ALVES",
      "taxa": "IPC-A +10,60%",
      "vencimento": "15/05/2031",
      "classe": "RENDA FIXA",
      "tipo": "IPCA+",
      "ticker": "",
      "moeda": "BRL",
      "custo_brl": 7500.24,
      "atual_brl": 7747.3,
      "status": "ativo"
    },
    {
      "id": 66,
      "data_aplicacao": "23/09/2024",
      "corretora": "XP",
      "titulo": "CRA AGROINSUMOS - MAI/2030 (4)",
      "emissor": "AGROINSUMOS",
      "taxa": "IPC-A +10,10%",
      "vencimento": "15/05/2030",
      "classe": "RENDA FIXA",
      "tipo": "IPCA+",
      "ticker": "",
      "moeda": "BRL",
      "custo_brl": 6590.8,
      "atual_brl": 7386.69,
      "status": "ativo"
    },
    {
      "id": 67,
      "data_aplicacao": "06/01/2026",
      "corretora": "XP",
      "titulo": "CRA USINA SÃO FRANCISCO BALBO - JUL/2028",
      "emissor": "USINA SÃO FRANCISCO",
      "taxa": "IPC-A +11,55%",
      "vencimento": "17/07/2028",
      "classe": "RENDA FIXA",
      "tipo": "IPCA+",
      "ticker": "",
      "moeda": "BRL",
      "custo_brl": 5068.28,
      "atual_brl": 5409.17,
      "status": "ativo"
    },
    {
      "id": 68,
      "data_aplicacao": "26/09/2024",
      "corretora": "XP",
      "titulo": "CRI MRV FLEX - DEZ/2032",
      "emissor": "MRV FLEX",
      "taxa": "IPC-A +8,95%",
      "vencimento": "15/12/2032",
      "classe": "RENDA FIXA",
      "tipo": "IPCA+",
      "ticker": "",
      "moeda": "BRL",
      "custo_brl": 4430.2,
      "atual_brl": 5302.14,
      "status": "ativo"
    },
    {
      "id": 69,
      "data_aplicacao": "",
      "corretora": "XP",
      "titulo": "TESOURO RENDA+ 2065 - IPCA +7,05%",
      "emissor": "GOV BR",
      "taxa": "IPCA +7,05%",
      "vencimento": "15/04/2065",
      "classe": "RENDA FIXA",
      "tipo": "IPCA+",
      "ticker": "",
      "moeda": "BRL",
      "custo_brl": 40853.0,
      "atual_brl": 40232.0,
      "status": "ativo"
    },
    {
      "id": 70,
      "data_aplicacao": "18/05/2026",
      "corretora": "XP",
      "titulo": "CRA MARFRIG - JAN/2032",
      "emissor": "MARFRIG",
      "taxa": "IPCA +10,39%",
      "vencimento": "15/01/2032",
      "classe": "RENDA FIXA",
      "tipo": "IPCA+",
      "ticker": "",
      "moeda": "BRL",
      "custo_brl": 43083.15,
      "atual_brl": 43083.15,
      "status": "ativo"
    },
    {
      "id": 71,
      "data_aplicacao": "11/06/2024",
      "corretora": "Banco Inter",
      "titulo": "LCI MENSAL IPCA + 5,84% - JUN/2027",
      "emissor": "INTER",
      "taxa": "IPCA +5,84%",
      "vencimento": "16/06/2027",
      "classe": "RENDA FIXA",
      "tipo": "IPCA+",
      "ticker": "",
      "moeda": "BRL",
      "custo_brl": 10000.0,
      "atual_brl": 10981.0,
      "status": "ativo"
    },
    {
      "id": 72,
      "data_aplicacao": "11/06/2024",
      "corretora": "Banco Inter",
      "titulo": "LCI IPCA 3 ANOS + 6,36%",
      "emissor": "INTER",
      "taxa": "IPCA +6,36%",
      "vencimento": "16/06/2027",
      "classe": "RENDA FIXA",
      "tipo": "IPCA+",
      "ticker": "",
      "moeda": "BRL",
      "custo_brl": 10000.0,
      "atual_brl": 12392.0,
      "status": "ativo"
    },
    {
      "id": 73,
      "data_aplicacao": "02/06/2025",
      "corretora": "Banco Inter",
      "titulo": "TESOURO RENDA+ 2060 IPCA +7,05%",
      "emissor": "GOV BR",
      "taxa": "IPCA +7,05%",
      "vencimento": "01/01/2060",
      "classe": "RENDA FIXA",
      "tipo": "IPCA+",
      "ticker": "",
      "moeda": "BRL",
      "custo_brl": 12004.5,
      "atual_brl": 13041.0,
      "status": "ativo"
    },
    {
      "id": 74,
      "data_aplicacao": "01/07/2025",
      "corretora": "Banco Inter",
      "titulo": "TESOURO RENDA+ 2065 IPCA +6,98%",
      "emissor": "GOV BR",
      "taxa": "IPCA +6,98%",
      "vencimento": "15/12/2065",
      "classe": "RENDA FIXA",
      "tipo": "IPCA+",
      "ticker": "",
      "moeda": "BRL",
      "custo_brl": 15075.41,
      "atual_brl": 15668.0,
      "status": "ativo"
    },
    {
      "id": 75,
      "data_aplicacao": "24/10/2024",
      "corretora": "BTG",
      "titulo": "DEB VIA BRASIL - IPCA +8,2% - DEZ/2030",
      "emissor": "VIA BRASIL",
      "taxa": "IPCA +8,2%",
      "vencimento": "15/12/2030",
      "classe": "RENDA FIXA",
      "tipo": "IPCA+",
      "ticker": "",
      "moeda": "BRL",
      "custo_brl": 29224.0,
      "atual_brl": 31819.0,
      "status": "ativo"
    },
    {
      "id": 76,
      "data_aplicacao": "14/03/2023",
      "corretora": "BTG",
      "titulo": "CRA COCAL - IPCA +8,22% - AGO/2030",
      "emissor": "COCAL",
      "taxa": "IPCA +8,22%",
      "vencimento": "15/08/2030",
      "classe": "RENDA FIXA",
      "tipo": "IPCA+",
      "ticker": "",
      "moeda": "BRL",
      "custo_brl": 19728.71,
      "atual_brl": 23964.0,
      "status": "ativo"
    },
    {
      "id": 77,
      "data_aplicacao": "03/02/2023",
      "corretora": "BTG",
      "titulo": "CRA CARAMURU - IPCA +8,18% - JUL/2029",
      "emissor": "CARAMURU",
      "taxa": "IPCA +8,18%",
      "vencimento": "16/07/2029",
      "classe": "RENDA FIXA",
      "tipo": "IPCA+",
      "ticker": "",
      "moeda": "BRL",
      "custo_brl": 29302.0,
      "atual_brl": 27798.0,
      "status": "ativo"
    },
    {
      "id": 78,
      "data_aplicacao": "28/03/2023",
      "corretora": "BTG",
      "titulo": "CRI MRV ENGENHARIA - IPCA +6,95% - FEV/2029",
      "emissor": "MRV",
      "taxa": "IPCA +6,95%",
      "vencimento": "15/02/2029",
      "classe": "RENDA FIXA",
      "tipo": "IPCA+",
      "ticker": "",
      "moeda": "BRL",
      "custo_brl": 20080.92,
      "atual_brl": 23560.0,
      "status": "ativo"
    },
    {
      "id": 79,
      "data_aplicacao": "06/08/2024",
      "corretora": "BTG",
      "titulo": "CRI MRV - IPCA +8,5% - AGO/2029",
      "emissor": "MRV",
      "taxa": "IPCA +8,5%",
      "vencimento": "15/08/2029",
      "classe": "RENDA FIXA",
      "tipo": "IPCA+",
      "ticker": "",
      "moeda": "BRL",
      "custo_brl": 19817.0,
      "atual_brl": 5709.0,
      "status": "ativo"
    },
    {
      "id": 80,
      "data_aplicacao": "30/07/2024",
      "corretora": "BTG",
      "titulo": "DEB LIGGA - IPCA +10% - JUL/2030",
      "emissor": "LIGGA",
      "taxa": "IPCA +10%",
      "vencimento": "15/09/2030",
      "classe": "RENDA FIXA",
      "tipo": "IPCA+",
      "ticker": "",
      "moeda": "BRL",
      "custo_brl": 9722.0,
      "atual_brl": 11051.0,
      "status": "ativo"
    },
    {
      "id": 81,
      "data_aplicacao": "24/09/2024",
      "corretora": "BTG",
      "titulo": "CRA CARAMURU - IPCA +8,15% - JUL/2029",
      "emissor": "CARAMURU",
      "taxa": "IPCA +8,15%",
      "vencimento": "15/07/2029",
      "classe": "RENDA FIXA",
      "tipo": "IPCA+",
      "ticker": "",
      "moeda": "BRL",
      "custo_brl": 13950.63,
      "atual_brl": 13073.0,
      "status": "ativo"
    },
    {
      "id": 82,
      "data_aplicacao": "24/09/2024",
      "corretora": "BTG",
      "titulo": "DEB LIGGA - IPCA +10% - SET/2030",
      "emissor": "LIGGA",
      "taxa": "IPCA +10%",
      "vencimento": "15/09/2030",
      "classe": "RENDA FIXA",
      "tipo": "IPCA+",
      "ticker": "",
      "moeda": "BRL",
      "custo_brl": 14734.95,
      "atual_brl": 17175.0,
      "status": "ativo"
    },
    {
      "id": 83,
      "data_aplicacao": "30/09/2024",
      "corretora": "BTG",
      "titulo": "DEB LIGGA - IPCA +10% - SET/2030 (2)",
      "emissor": "LIGGA",
      "taxa": "IPCA +10%",
      "vencimento": "15/09/2030",
      "classe": "RENDA FIXA",
      "tipo": "IPCA+",
      "ticker": "",
      "moeda": "BRL",
      "custo_brl": 16875.39,
      "atual_brl": 19629.0,
      "status": "ativo"
    },
    {
      "id": 84,
      "data_aplicacao": "30/09/2024",
      "corretora": "BTG",
      "titulo": "CRI URBA - IPCA +9% - MAR/2033",
      "emissor": "URBA",
      "taxa": "IPCA +9%",
      "vencimento": "31/03/2033",
      "classe": "RENDA FIXA",
      "tipo": "IPCA+",
      "ticker": "",
      "moeda": "BRL",
      "custo_brl": 29382.69,
      "atual_brl": 22183.0,
      "status": "ativo"
    },
    {
      "id": 85,
      "data_aplicacao": "30/09/2024",
      "corretora": "BTG",
      "titulo": "DEB VERO S.A. - IPCA +8,1% - MAR/2030",
      "emissor": "VERO",
      "taxa": "IPCA +8,1%",
      "vencimento": "17/03/2030",
      "classe": "RENDA FIXA",
      "tipo": "IPCA+",
      "ticker": "",
      "moeda": "BRL",
      "custo_brl": 14338.42,
      "atual_brl": 15616.0,
      "status": "ativo"
    },
    {
      "id": 86,
      "data_aplicacao": "14/10/2024",
      "corretora": "BTG",
      "titulo": "DEB NORTE ENERGIA - IPCA +8,2% - DEZ/2030",
      "emissor": "NORTE ENERGIA",
      "taxa": "IPCA +8,2%",
      "vencimento": "15/05/2030",
      "classe": "RENDA FIXA",
      "tipo": "IPCA+",
      "ticker": "",
      "moeda": "BRL",
      "custo_brl": 29122.14,
      "atual_brl": 22244.0,
      "status": "ativo"
    },
    {
      "id": 87,
      "data_aplicacao": "14/10/2024",
      "corretora": "BTG",
      "titulo": "DEB TRIPLE PLAY - IPCA +10% - AGO/2029",
      "emissor": "ALARES INTERNET",
      "taxa": "IPCA +10%",
      "vencimento": "15/08/2029",
      "classe": "RENDA FIXA",
      "tipo": "IPCA+",
      "ticker": "",
      "moeda": "BRL",
      "custo_brl": 4160.0,
      "atual_brl": 4640.0,
      "status": "ativo"
    },
    {
      "id": 88,
      "data_aplicacao": "24/10/2024",
      "corretora": "BTG",
      "titulo": "CRI LT VISTAMAR - IPCA +12% - JUN/2026",
      "emissor": "LT EMPRENDIMENTOS",
      "taxa": "IPCA +12%",
      "vencimento": "15/06/2026",
      "classe": "RENDA FIXA",
      "tipo": "IPCA+",
      "ticker": "",
      "moeda": "BRL",
      "custo_brl": 19665.0,
      "atual_brl": 15302.0,
      "status": "ativo"
    },
    {
      "id": 89,
      "data_aplicacao": "28/10/2024",
      "corretora": "BTG",
      "titulo": "CRI LT VISTAMAR - IPCA +12% - NOV/2026",
      "emissor": "LT EMPRENDIMENTOS",
      "taxa": "IPCA +12%",
      "vencimento": "15/06/2026",
      "classe": "RENDA FIXA",
      "tipo": "IPCA+",
      "ticker": "",
      "moeda": "BRL",
      "custo_brl": 15302.0,
      "atual_brl": 12264.0,
      "status": "ativo"
    },
    {
      "id": 90,
      "data_aplicacao": "24/01/2025",
      "corretora": "BTG",
      "titulo": "TESOURO IPCA 2060 +7,20%",
      "emissor": "GOV BR",
      "taxa": "IPCA +7,20%",
      "vencimento": "15/08/2060",
      "classe": "RENDA FIXA",
      "tipo": "IPCA+",
      "ticker": "",
      "moeda": "BRL",
      "custo_brl": 42661.89,
      "atual_brl": 44466.0,
      "status": "ativo"
    },
    {
      "id": 91,
      "data_aplicacao": "08/01/2025",
      "corretora": "BTG",
      "titulo": "TESOURO IPCA 2045 +7,05%",
      "emissor": "GOV BR",
      "taxa": "IPCA +7,05%",
      "vencimento": "15/05/2045",
      "classe": "RENDA FIXA",
      "tipo": "IPCA+",
      "ticker": "",
      "moeda": "BRL",
      "custo_brl": 63677.56,
      "atual_brl": 66790.0,
      "status": "ativo"
    },
    {
      "id": 92,
      "data_aplicacao": "31/01/2025",
      "corretora": "BTG",
      "titulo": "CRI MELCHIORETTO - IPCA +10,5% - OUT/2031",
      "emissor": "MS EMPREENDIMENTOS",
      "taxa": "IPCA +10,5%",
      "vencimento": "17/10/2031",
      "classe": "RENDA FIXA",
      "tipo": "IPCA+",
      "ticker": "",
      "moeda": "BRL",
      "custo_brl": 30404.97,
      "atual_brl": 28743.0,
      "status": "ativo"
    },
    {
      "id": 93,
      "data_aplicacao": "07/01/2025",
      "corretora": "BTG",
      "titulo": "DEB ALCOESTE - IPCA +8,7% - DEZ/2027",
      "emissor": "ALCOESTE",
      "taxa": "IPCA +8,7%",
      "vencimento": "15/12/2027",
      "classe": "RENDA FIXA",
      "tipo": "IPCA+",
      "ticker": "",
      "moeda": "BRL",
      "custo_brl": 10403.0,
      "atual_brl": 7616.0,
      "status": "ativo"
    },
    {
      "id": 94,
      "data_aplicacao": "18/06/2025",
      "corretora": "BTG",
      "titulo": "TESOURO RENDA+ IPCA +7,32%",
      "emissor": "GOV BR",
      "taxa": "IPCA +7,32%",
      "vencimento": "01/01/2060",
      "classe": "RENDA FIXA",
      "tipo": "IPCA+",
      "ticker": "",
      "moeda": "BRL",
      "custo_brl": 7264.3,
      "atual_brl": 7332.0,
      "status": "ativo"
    },
    {
      "id": 95,
      "data_aplicacao": "19/08/2025",
      "corretora": "BTG",
      "titulo": "DEB VBRR11 - IPCA +9,52% - DEZ/2030",
      "emissor": "VIA BRASIL",
      "taxa": "IPCA +9,52%",
      "vencimento": "15/10/2030",
      "classe": "RENDA FIXA",
      "tipo": "IPCA+",
      "ticker": "",
      "moeda": "BRL",
      "custo_brl": 27853.0,
      "atual_brl": 29516.0,
      "status": "ativo"
    },
    {
      "id": 96,
      "data_aplicacao": "30/09/2025",
      "corretora": "BTG",
      "titulo": "DEB USCA12 - IPCA +9,32%",
      "emissor": "USINA CAETES",
      "taxa": "IPCA +9,32%",
      "vencimento": "16/06/2031",
      "classe": "RENDA FIXA",
      "tipo": "IPCA+",
      "ticker": "",
      "moeda": "BRL",
      "custo_brl": 32457.0,
      "atual_brl": 34019.0,
      "status": "ativo"
    },
    {
      "id": 97,
      "data_aplicacao": "06/01/2026",
      "corretora": "XP",
      "titulo": "CRA ALIBEM - DEZ/2030",
      "emissor": "ALIBEM",
      "taxa": "15,04%",
      "vencimento": "18/12/2030",
      "classe": "RENDA FIXA",
      "tipo": "PRÉ",
      "ticker": "",
      "moeda": "BRL",
      "custo_brl": 40003.31,
      "atual_brl": 42055.97,
      "status": "ativo"
    },
    {
      "id": 98,
      "data_aplicacao": "16/10/2024",
      "corretora": "XP",
      "titulo": "CRA MINERVA - MAR/2031",
      "emissor": "MINERVA",
      "taxa": "13,15%",
      "vencimento": "17/03/2031",
      "classe": "RENDA FIXA",
      "tipo": "PRÉ",
      "ticker": "",
      "moeda": "BRL",
      "custo_brl": 39354.81,
      "atual_brl": 40465.18,
      "status": "ativo"
    },
    {
      "id": 99,
      "data_aplicacao": "22/11/2024",
      "corretora": "XP",
      "titulo": "CRI PATRIMAR - NOV/2029",
      "emissor": "PATRIMAR",
      "taxa": "15,30%",
      "vencimento": "23/11/2029",
      "classe": "RENDA FIXA",
      "tipo": "PRÉ",
      "ticker": "",
      "moeda": "BRL",
      "custo_brl": 32840.96,
      "atual_brl": 35140.87,
      "status": "ativo"
    },
    {
      "id": 100,
      "data_aplicacao": "03/06/2025",
      "corretora": "XP",
      "titulo": "DEB V.TAL - ABR/2032",
      "emissor": "V.TAL",
      "taxa": "14,95%",
      "vencimento": "15/04/2032",
      "classe": "RENDA FIXA",
      "tipo": "PRÉ",
      "ticker": "",
      "moeda": "BRL",
      "custo_brl": 32114.17,
      "atual_brl": 32502.82,
      "status": "ativo"
    },
    {
      "id": 101,
      "data_aplicacao": "30/09/2025",
      "corretora": "XP",
      "titulo": "CRI DASA - JAN/2031",
      "emissor": "DASA",
      "taxa": "16,55%",
      "vencimento": "15/01/2031",
      "classe": "RENDA FIXA",
      "tipo": "PRÉ",
      "ticker": "",
      "moeda": "BRL",
      "custo_brl": 29288.43,
      "atual_brl": 30993.1,
      "status": "ativo"
    },
    {
      "id": 102,
      "data_aplicacao": "14/10/2024",
      "corretora": "XP",
      "titulo": "CDCA VAMOS - SET/2031",
      "emissor": "VAMOS",
      "taxa": "13,50%",
      "vencimento": "15/09/2031",
      "classe": "RENDA FIXA",
      "tipo": "PRÉ",
      "ticker": "",
      "moeda": "BRL",
      "custo_brl": 30163.84,
      "atual_brl": 30790.59,
      "status": "ativo"
    },
    {
      "id": 103,
      "data_aplicacao": "03/06/2025",
      "corretora": "XP",
      "titulo": "CRA UBYFOL - MAI/2028",
      "emissor": "UBYFOL",
      "taxa": "18,00%",
      "vencimento": "22/05/2028",
      "classe": "RENDA FIXA",
      "tipo": "PRÉ",
      "ticker": "",
      "moeda": "BRL",
      "custo_brl": 27999.56,
      "atual_brl": 28351.61,
      "status": "ativo"
    },
    {
      "id": 104,
      "data_aplicacao": "19/08/2025",
      "corretora": "XP",
      "titulo": "CRA UBYFOL - MAI/2028 (2)",
      "emissor": "UBYFOL",
      "taxa": "17,45%",
      "vencimento": "22/05/2028",
      "classe": "RENDA FIXA",
      "tipo": "PRÉ",
      "ticker": "",
      "moeda": "BRL",
      "custo_brl": 25260.35,
      "atual_brl": 25514.73,
      "status": "ativo"
    },
    {
      "id": 105,
      "data_aplicacao": "03/09/2025",
      "corretora": "XP",
      "titulo": "CRA UISA - JUL/2031",
      "emissor": "UISA",
      "taxa": "17,05%",
      "vencimento": "15/07/2031",
      "classe": "RENDA FIXA",
      "tipo": "PRÉ",
      "ticker": "",
      "moeda": "BRL",
      "custo_brl": 25036.88,
      "atual_brl": 25382.55,
      "status": "ativo"
    },
    {
      "id": 106,
      "data_aplicacao": "19/08/2025",
      "corretora": "XP",
      "titulo": "CRA UISA - JUL/2031 (2)",
      "emissor": "UISA",
      "taxa": "17,10%",
      "vencimento": "15/07/2031",
      "classe": "RENDA FIXA",
      "tipo": "PRÉ",
      "ticker": "",
      "moeda": "BRL",
      "custo_brl": 24999.19,
      "atual_brl": 25346.92,
      "status": "ativo"
    },
    {
      "id": 107,
      "data_aplicacao": "11/02/2026",
      "corretora": "XP",
      "titulo": "CRI BRZ - DEZ/2030",
      "emissor": "BRZ",
      "taxa": "15,45%",
      "vencimento": "16/12/2030",
      "classe": "RENDA FIXA",
      "tipo": "PRÉ",
      "ticker": "",
      "moeda": "BRL",
      "custo_brl": 24030.15,
      "atual_brl": 24056.26,
      "status": "ativo"
    },
    {
      "id": 108,
      "data_aplicacao": "15/10/2025",
      "corretora": "XP",
      "titulo": "CRA ACP Bioenergia - NOV/2028",
      "emissor": "ACP Bioenergia",
      "taxa": "16,20%",
      "vencimento": "21/11/2028",
      "classe": "RENDA FIXA",
      "tipo": "PRÉ",
      "ticker": "",
      "moeda": "BRL",
      "custo_brl": 23707.06,
      "atual_brl": 23907.42,
      "status": "ativo"
    },
    {
      "id": 109,
      "data_aplicacao": "24/11/2025",
      "corretora": "XP",
      "titulo": "CRI SOLFACIL SÊNIOR - SET/2033",
      "emissor": "SOLFACIL SÊNIOR",
      "taxa": "15,40%",
      "vencimento": "22/09/2033",
      "classe": "RENDA FIXA",
      "tipo": "PRÉ",
      "ticker": "",
      "moeda": "BRL",
      "custo_brl": 22349.5,
      "atual_brl": 23298.7,
      "status": "ativo"
    },
    {
      "id": 110,
      "data_aplicacao": "22/05/2025",
      "corretora": "XP",
      "titulo": "CRI BILD - JAN/2030",
      "emissor": "BILD",
      "taxa": "15,40%",
      "vencimento": "16/01/2030",
      "classe": "RENDA FIXA",
      "tipo": "PRÉ",
      "ticker": "",
      "moeda": "BRL",
      "custo_brl": 21919.97,
      "atual_brl": 22870.33,
      "status": "ativo"
    },
    {
      "id": 111,
      "data_aplicacao": "16/09/2024",
      "corretora": "XP",
      "titulo": "CRA FS BIO - JUL/2030",
      "emissor": "FS BIO",
      "taxa": "14,40%",
      "vencimento": "15/07/2030",
      "classe": "RENDA FIXA",
      "tipo": "PRÉ",
      "ticker": "",
      "moeda": "BRL",
      "custo_brl": 20105.98,
      "atual_brl": 20316.78,
      "status": "ativo"
    },
    {
      "id": 112,
      "data_aplicacao": "18/02/2026",
      "corretora": "XP",
      "titulo": "CRI BRZ - DEZ/2030 (2)",
      "emissor": "BRZ",
      "taxa": "15,40%",
      "vencimento": "16/12/2030",
      "classe": "RENDA FIXA",
      "tipo": "PRÉ",
      "ticker": "",
      "moeda": "BRL",
      "custo_brl": 19048.03,
      "atual_brl": 19067.39,
      "status": "ativo"
    },
    {
      "id": 113,
      "data_aplicacao": "06/01/2026",
      "corretora": "XP",
      "titulo": "CRI SOLFACIL SÊNIOR - SET/2033 (2)",
      "emissor": "SOLFACIL SÊNIOR",
      "taxa": "15,50%",
      "vencimento": "22/09/2033",
      "classe": "RENDA FIXA",
      "tipo": "PRÉ",
      "ticker": "",
      "moeda": "BRL",
      "custo_brl": 18062.13,
      "atual_brl": 18566.2,
      "status": "ativo"
    },
    {
      "id": 114,
      "data_aplicacao": "15/12/2025",
      "corretora": "XP",
      "titulo": "CRI SOLFACIL SÊNIOR - SET/2033 (3)",
      "emissor": "SOLFACIL SÊNIOR",
      "taxa": "15,40%",
      "vencimento": "22/09/2033",
      "classe": "RENDA FIXA",
      "tipo": "PRÉ",
      "ticker": "",
      "moeda": "BRL",
      "custo_brl": 17115.86,
      "atual_brl": 17707.01,
      "status": "ativo"
    },
    {
      "id": 115,
      "data_aplicacao": "16/03/2026",
      "corretora": "XP",
      "titulo": "CRA NEOMILLE - DEZ/2032",
      "emissor": "NEOMILLE (CERRADINHO)",
      "taxa": "14,90%",
      "vencimento": "15/12/2032",
      "classe": "RENDA FIXA",
      "tipo": "PRÉ",
      "ticker": "",
      "moeda": "BRL",
      "custo_brl": 17018.23,
      "atual_brl": 17426.37,
      "status": "ativo"
    },
    {
      "id": 116,
      "data_aplicacao": "17/09/2024",
      "corretora": "XP",
      "titulo": "CRI DASA - JAN/2031 (2)",
      "emissor": "DASA",
      "taxa": "14,25%",
      "vencimento": "15/01/2031",
      "classe": "RENDA FIXA",
      "tipo": "PRÉ",
      "ticker": "",
      "moeda": "BRL",
      "custo_brl": 16122.63,
      "atual_brl": 17006.38,
      "status": "ativo"
    },
    {
      "id": 117,
      "data_aplicacao": "11/09/2024",
      "corretora": "XP",
      "titulo": "DEB ORIGEM ENERGIA - DEZ/2035",
      "emissor": "ORIGEM ENERGIA",
      "taxa": "13,55%",
      "vencimento": "15/12/2035",
      "classe": "RENDA FIXA",
      "tipo": "PRÉ",
      "ticker": "",
      "moeda": "BRL",
      "custo_brl": 15411.55,
      "atual_brl": 16209.48,
      "status": "ativo"
    },
    {
      "id": 118,
      "data_aplicacao": "24/09/2024",
      "corretora": "XP",
      "titulo": "DEB ORIGEM ENERGIA - DEZ/2035 (2)",
      "emissor": "ORIGEM ENERGIA",
      "taxa": "14,10%",
      "vencimento": "15/12/2035",
      "classe": "RENDA FIXA",
      "tipo": "PRÉ",
      "ticker": "",
      "moeda": "BRL",
      "custo_brl": 15025.59,
      "atual_brl": 15872.15,
      "status": "ativo"
    },
    {
      "id": 119,
      "data_aplicacao": "24/09/2024",
      "corretora": "XP",
      "titulo": "CRI SALTA - MAR/2029",
      "emissor": "SALTA",
      "taxa": "13,65%",
      "vencimento": "15/03/2029",
      "classe": "RENDA FIXA",
      "tipo": "PRÉ",
      "ticker": "",
      "moeda": "BRL",
      "custo_brl": 15087.75,
      "atual_brl": 15715.34,
      "status": "ativo"
    },
    {
      "id": 120,
      "data_aplicacao": "01/07/2025",
      "corretora": "XP",
      "titulo": "CRA UBYFOL - MAI/2028 (3)",
      "emissor": "UBYFOL",
      "taxa": "17,25%",
      "vencimento": "22/05/2028",
      "classe": "RENDA FIXA",
      "tipo": "PRÉ",
      "ticker": "",
      "moeda": "BRL",
      "custo_brl": 14207.2,
      "atual_brl": 14329.51,
      "status": "ativo"
    },
    {
      "id": 121,
      "data_aplicacao": "11/09/2024",
      "corretora": "XP",
      "titulo": "CRI SALTA - MAR/2029 (2)",
      "emissor": "SALTA",
      "taxa": "13,15%",
      "vencimento": "15/03/2029",
      "classe": "RENDA FIXA",
      "tipo": "PRÉ",
      "ticker": "",
      "moeda": "BRL",
      "custo_brl": 13386.07,
      "atual_brl": 13873.4,
      "status": "ativo"
    },
    {
      "id": 122,
      "data_aplicacao": "03/10/2024",
      "corretora": "XP",
      "titulo": "CRA ACP Bioenergia - NOV/2028 (2)",
      "emissor": "ACP Bioenergia",
      "taxa": "14,75%",
      "vencimento": "21/11/2028",
      "classe": "RENDA FIXA",
      "tipo": "PRÉ",
      "ticker": "",
      "moeda": "BRL",
      "custo_brl": 10656.88,
      "atual_brl": 10701.59,
      "status": "ativo"
    },
    {
      "id": 123,
      "data_aplicacao": "18/12/2024",
      "corretora": "XP",
      "titulo": "CRA GRUPO JB - OUT/2028",
      "emissor": "GRUPO JB",
      "taxa": "18,90%",
      "vencimento": "25/10/2028",
      "classe": "RENDA FIXA",
      "tipo": "PRÉ",
      "ticker": "",
      "moeda": "BRL",
      "custo_brl": 5501.1,
      "atual_brl": 5667.94,
      "status": "ativo"
    },
    {
      "id": 124,
      "data_aplicacao": "23/12/2024",
      "corretora": "XP",
      "titulo": "CRA GRUPO JB - OUT/2028 (2)",
      "emissor": "GRUPO JB",
      "taxa": "18,30%",
      "vencimento": "25/10/2028",
      "classe": "RENDA FIXA",
      "tipo": "PRÉ",
      "ticker": "",
      "moeda": "BRL",
      "custo_brl": 3485.53,
      "atual_brl": 3564.71,
      "status": "ativo"
    },
    {
      "id": 125,
      "data_aplicacao": "06/01/2025",
      "corretora": "XP",
      "titulo": "CRA REFRESCOS BANDEIRANTES - NOV/2032",
      "emissor": "REFRESCOS BANDEIRANTES",
      "taxa": "15,45%",
      "vencimento": "16/11/2032",
      "classe": "RENDA FIXA",
      "tipo": "PRÉ",
      "ticker": "",
      "moeda": "BRL",
      "custo_brl": 2767.82,
      "atual_brl": 2798.6,
      "status": "ativo"
    },
    {
      "id": 126,
      "data_aplicacao": "01/07/2025",
      "corretora": "Banco Inter",
      "titulo": "CRA BRASKEN - IPCA +10,5% - DEZ/2028",
      "emissor": "BRASKEN",
      "taxa": "IPCA +10,5%",
      "vencimento": "15/12/2028",
      "classe": "RENDA FIXA",
      "tipo": "PRÉ",
      "ticker": "",
      "moeda": "BRL",
      "custo_brl": 11487.0,
      "atual_brl": 12561.0,
      "status": "ativo"
    },
    {
      "id": 127,
      "data_aplicacao": "02/10/2024",
      "corretora": "BTG",
      "titulo": "DEB TECPAR - PRÉ 15% - JUN/2030",
      "emissor": "BRASIL TECNOLOGIA",
      "taxa": "15,00%",
      "vencimento": "15/05/2030",
      "classe": "RENDA FIXA",
      "tipo": "PRÉ",
      "ticker": "",
      "moeda": "BRL",
      "custo_brl": 14755.0,
      "atual_brl": 15056.0,
      "status": "ativo"
    },
    {
      "id": 128,
      "data_aplicacao": "02/10/2024",
      "corretora": "BTG",
      "titulo": "DEB TRIPLE PLAY - PRÉ 15,2% - JUL/2031",
      "emissor": "TRIPLE PLAY",
      "taxa": "15,20%",
      "vencimento": "15/07/2031",
      "classe": "RENDA FIXA",
      "tipo": "PRÉ",
      "ticker": "",
      "moeda": "BRL",
      "custo_brl": 14228.0,
      "atual_brl": 13764.0,
      "status": "ativo"
    },
    {
      "id": 129,
      "data_aplicacao": "04/10/2024",
      "corretora": "BTG",
      "titulo": "DEB TRIPLE PLAY - PRÉ 15,2% - MAI/2030",
      "emissor": "TRIPLE PLAY",
      "taxa": "15,20%",
      "vencimento": "15/05/2030",
      "classe": "RENDA FIXA",
      "tipo": "PRÉ",
      "ticker": "",
      "moeda": "BRL",
      "custo_brl": 11192.05,
      "atual_brl": 10815.0,
      "status": "ativo"
    },
    {
      "id": 130,
      "data_aplicacao": "14/10/2024",
      "corretora": "BTG",
      "titulo": "DEB TECPAR - PRÉ 15,5% - JUL/2031",
      "emissor": "BRASIL TECNOLOGIA",
      "taxa": "15,50%",
      "vencimento": "15/07/2031",
      "classe": "RENDA FIXA",
      "tipo": "PRÉ",
      "ticker": "",
      "moeda": "BRL",
      "custo_brl": 14571.73,
      "atual_brl": 14859.0,
      "status": "ativo"
    },
    {
      "id": 131,
      "data_aplicacao": "05/11/2024",
      "corretora": "BTG",
      "titulo": "FII RIZA EQUITUS - PRÉ 14% - OUT/2029",
      "emissor": "RIZA",
      "taxa": "14,00%",
      "vencimento": "01/11/2029",
      "classe": "RENDA FIXA",
      "tipo": "PRÉ",
      "ticker": "",
      "moeda": "BRL",
      "custo_brl": 30000.0,
      "atual_brl": 35434.0,
      "status": "ativo"
    },
    {
      "id": 132,
      "data_aplicacao": "17/10/2024",
      "corretora": "BTG",
      "titulo": "CDB PICPAY BANK - PRÉ 14,15% - OUT/2027",
      "emissor": "PICPAY",
      "taxa": "14,15%",
      "vencimento": "18/10/2027",
      "classe": "RENDA FIXA",
      "tipo": "PRÉ",
      "ticker": "",
      "moeda": "BRL",
      "custo_brl": 28000.0,
      "atual_brl": 33325.0,
      "status": "ativo"
    },
    {
      "id": 133,
      "data_aplicacao": "21/11/2024",
      "corretora": "BTG",
      "titulo": "CRA ALCOESTE - CDI +3,50% - NOV/2029",
      "emissor": "ALCOESTE",
      "taxa": "CDI +3,52%",
      "vencimento": "23/11/2029",
      "classe": "RENDA FIXA",
      "tipo": "PRÉ",
      "ticker": "",
      "moeda": "BRL",
      "custo_brl": 24810.0,
      "atual_brl": 24609.0,
      "status": "ativo"
    },
    {
      "id": 134,
      "data_aplicacao": "31/01/2025",
      "corretora": "BTG",
      "titulo": "DEB ORIGEN - PRÉ 15,4%",
      "emissor": "ORIGEM ENERGIA",
      "taxa": "15,40%",
      "vencimento": "15/12/2035",
      "classe": "RENDA FIXA",
      "tipo": "PRÉ",
      "ticker": "",
      "moeda": "BRL",
      "custo_brl": 30836.0,
      "atual_brl": 32222.0,
      "status": "ativo"
    },
    {
      "id": 135,
      "data_aplicacao": "16/03/2026",
      "corretora": "XP",
      "titulo": "CRA CORURIPE - NOV/2030",
      "emissor": "CORURIPE",
      "taxa": "CDI +4,40%",
      "vencimento": "25/11/2030",
      "classe": "RENDA FIXA",
      "tipo": "CDI",
      "ticker": "",
      "moeda": "BRL",
      "custo_brl": 44124.18,
      "atual_brl": 45497.14,
      "status": "ativo"
    },
    {
      "id": 136,
      "data_aplicacao": "22/01/2025",
      "corretora": "XP",
      "titulo": "CRI CIBRA - SET/2028",
      "emissor": "CIBRA",
      "taxa": "CDI +4,39%",
      "vencimento": "01/09/2028",
      "classe": "RENDA FIXA",
      "tipo": "CDI",
      "ticker": "",
      "moeda": "BRL",
      "custo_brl": 33304.9,
      "atual_brl": 33204.42,
      "status": "ativo"
    },
    {
      "id": 137,
      "data_aplicacao": "11/02/2025",
      "corretora": "XP",
      "titulo": "DEB GPA - MAI/2028",
      "emissor": "GPA",
      "taxa": "CDI +8,40%",
      "vencimento": "10/05/2028",
      "classe": "RENDA FIXA",
      "tipo": "CDI",
      "ticker": "",
      "moeda": "BRL",
      "custo_brl": 19086.05,
      "atual_brl": 21213.45,
      "status": "ativo"
    },
    {
      "id": 138,
      "data_aplicacao": "14/11/2024",
      "corretora": "XP",
      "titulo": "CRA MAESTRO - DEZ/2028",
      "emissor": "MAESTRO",
      "taxa": "CDI +4,10%",
      "vencimento": "15/12/2028",
      "classe": "RENDA FIXA",
      "tipo": "CDI",
      "ticker": "",
      "moeda": "BRL",
      "custo_brl": 13545.04,
      "atual_brl": 13835.62,
      "status": "ativo"
    },
    {
      "id": 139,
      "data_aplicacao": "05/02/2025",
      "corretora": "XP",
      "titulo": "CRA GRUPO JB - OUT/2030",
      "emissor": "GRUPO JB",
      "taxa": "CDI +3,96%",
      "vencimento": "25/10/2030",
      "classe": "RENDA FIXA",
      "tipo": "CDI",
      "ticker": "",
      "moeda": "BRL",
      "custo_brl": 11543.81,
      "atual_brl": 11636.52,
      "status": "ativo"
    },
    {
      "id": 140,
      "data_aplicacao": "19/02/2025",
      "corretora": "XP",
      "titulo": "CRA GRUPO JB - OUT/2030 (2)",
      "emissor": "GRUPO JB",
      "taxa": "CDI +4,10%",
      "vencimento": "25/10/2030",
      "classe": "RENDA FIXA",
      "tipo": "CDI",
      "ticker": "",
      "moeda": "BRL",
      "custo_brl": 9857.63,
      "atual_brl": 9948.96,
      "status": "ativo"
    },
    {
      "id": 141,
      "data_aplicacao": "05/02/2025",
      "corretora": "XP",
      "titulo": "CRA MAESTRO - DEZ/2028 (2)",
      "emissor": "MAESTRO",
      "taxa": "CDI +4,10%",
      "vencimento": "15/12/2028",
      "classe": "RENDA FIXA",
      "tipo": "CDI",
      "ticker": "",
      "moeda": "BRL",
      "custo_brl": 9543.59,
      "atual_brl": 9766.32,
      "status": "ativo"
    },
    {
      "id": 142,
      "data_aplicacao": "16/03/2026",
      "corretora": "XP",
      "titulo": "COMPROMISSADA - JAN/2028",
      "emissor": "COMPROMISSADA",
      "taxa": "CDI +0,91%",
      "vencimento": "17/01/2028",
      "classe": "RENDA FIXA",
      "tipo": "CDI",
      "ticker": "",
      "moeda": "BRL",
      "custo_brl": -44754.0,
      "atual_brl": -45306.99,
      "status": "ativo"
    },
    {
      "id": 143,
      "data_aplicacao": "14/10/2024",
      "corretora": "BTG",
      "titulo": "FIDC ARTESANAL - CDI +3% - OUT/2026",
      "emissor": "ARTESANAL",
      "taxa": "CDI +3%",
      "vencimento": "05/10/2026",
      "classe": "RENDA FIXA",
      "tipo": "CDI",
      "ticker": "",
      "moeda": "BRL",
      "custo_brl": 30000.0,
      "atual_brl": 36554.0,
      "status": "ativo"
    },
    {
      "id": 144,
      "data_aplicacao": "22/10/2024",
      "corretora": "BTG",
      "titulo": "CRA FRIGOL - CDI +3,5% - OUT/2030",
      "emissor": "FRIGOL",
      "taxa": "CDI +3,5%",
      "vencimento": "15/10/2030",
      "classe": "RENDA FIXA",
      "tipo": "CDI",
      "ticker": "",
      "moeda": "BRL",
      "custo_brl": 17297.0,
      "atual_brl": 15684.0,
      "status": "ativo"
    },
    {
      "id": 145,
      "data_aplicacao": "24/10/2024",
      "corretora": "BTG",
      "titulo": "CRA FRIGOL - CDI +3,50% - OUT/2030 (2)",
      "emissor": "FRIGOL",
      "taxa": "CDI +3,50%",
      "vencimento": "19/10/2030",
      "classe": "RENDA FIXA",
      "tipo": "CDI",
      "ticker": "",
      "moeda": "BRL",
      "custo_brl": 14282.71,
      "atual_brl": 12916.0,
      "status": "ativo"
    },
    {
      "id": 146,
      "data_aplicacao": "24/10/2024",
      "corretora": "BTG",
      "titulo": "CRI YOU INC - CDI +3% - NOV/2026",
      "emissor": "YOU INC.",
      "taxa": "CDI +3%",
      "vencimento": "09/11/2026",
      "classe": "RENDA FIXA",
      "tipo": "CDI",
      "ticker": "",
      "moeda": "BRL",
      "custo_brl": 5717.0,
      "atual_brl": 5123.0,
      "status": "ativo"
    },
    {
      "id": 147,
      "data_aplicacao": "13/11/2024",
      "corretora": "BTG",
      "titulo": "CRA FRIGOL - CDI +3,50% - OUT/2030 (3)",
      "emissor": "FRIGOL",
      "taxa": "CDI +3,50%",
      "vencimento": "15/10/2030",
      "classe": "RENDA FIXA",
      "tipo": "CDI",
      "ticker": "",
      "moeda": "BRL",
      "custo_brl": 9231.54,
      "atual_brl": 8302.0,
      "status": "ativo"
    },
    {
      "id": 148,
      "data_aplicacao": "21/01/2025",
      "corretora": "BTG",
      "titulo": "CRI ARENA MRV - CDI +4,5%",
      "emissor": "MRV",
      "taxa": "CDI +4,5%",
      "vencimento": "24/09/2029",
      "classe": "RENDA FIXA",
      "tipo": "CDI",
      "ticker": "",
      "moeda": "BRL",
      "custo_brl": 25148.53,
      "atual_brl": 18039.0,
      "status": "ativo"
    },
    {
      "id": 149,
      "data_aplicacao": "29/01/2025",
      "corretora": "BTG",
      "titulo": "CRI SQUARE LIFE - CDI +3,75%",
      "emissor": "SQUARE LIFE",
      "taxa": "CDI +3,75%",
      "vencimento": "26/12/2029",
      "classe": "RENDA FIXA",
      "tipo": "CDI",
      "ticker": "",
      "moeda": "BRL",
      "custo_brl": 30000.0,
      "atual_brl": 24531.0,
      "status": "ativo"
    },
    {
      "id": 150,
      "data_aplicacao": "09/07/2025",
      "corretora": "CEF",
      "titulo": "CAIXA FIC PREV 250 RF PÓS FIXADO",
      "emissor": "CAIXA",
      "taxa": "CDI",
      "vencimento": "",
      "classe": "RENDA FIXA",
      "tipo": "CDI",
      "ticker": "",
      "moeda": "BRL",
      "custo_brl": 26754.0,
      "atual_brl": 26754.0,
      "status": "ativo"
    },
    {
      "id": 151,
      "data_aplicacao": "09/08/2023",
      "corretora": "BANRISUL",
      "titulo": "CONSÓRCIO AUTOCRÉDITO 30 MIL",
      "emissor": "BANRISUL",
      "taxa": "CDI",
      "vencimento": "",
      "classe": "OUTROS",
      "tipo": "CDI",
      "ticker": "",
      "moeda": "BRL",
      "custo_brl": 40000.0,
      "atual_brl": 40000.0,
      "status": "ativo"
    },
    {
      "id": 152,
      "data_aplicacao": "09/08/2023",
      "corretora": "BANRISUL",
      "titulo": "CONSÓRCIO AUTOCRÉDITO 40 MIL",
      "emissor": "BANRISUL",
      "taxa": "CDI",
      "vencimento": "",
      "classe": "OUTROS",
      "tipo": "CDI",
      "ticker": "",
      "moeda": "BRL",
      "custo_brl": 42000.0,
      "atual_brl": 42000.0,
      "status": "ativo"
    },
    {
      "id": 153,
      "data_aplicacao": "22/01/2025",
      "corretora": "Banco Inter",
      "titulo": "BRGV USD - PRÉ 6,63% - JAN/2034",
      "emissor": "TESOURO BR",
      "taxa": "USD +6,63%",
      "vencimento": "20/01/2034",
      "classe": "RENDA FIXA",
      "tipo": "BONDS",
      "ticker": "",
      "moeda": "BRL",
      "custo_brl": "",
      "atual_brl": 28998.29,
      "status": "ativo"
    },
    {
      "id": 154,
      "data_aplicacao": "05/02/2025",
      "corretora": "Banco Inter",
      "titulo": "PEMEX - USD - PRÉ 6,625% - JUN/2035",
      "emissor": "PETROLEO MEXICANO",
      "taxa": "USD +6,625%",
      "vencimento": "15/06/2035",
      "classe": "RENDA FIXA",
      "tipo": "BONDS",
      "ticker": "",
      "moeda": "BRL",
      "custo_brl": "",
      "atual_brl": 49182.23,
      "status": "ativo"
    },
    {
      "id": 155,
      "data_aplicacao": "13/09/2024",
      "corretora": "AVENUE",
      "titulo": "CSN - USD +8,2% - JAN/2028",
      "emissor": "CSN",
      "taxa": "USD +8,23%",
      "vencimento": "28/01/2028",
      "classe": "RENDA FIXA",
      "tipo": "BONDS",
      "ticker": "",
      "moeda": "BRL",
      "custo_brl": "",
      "atual_brl": 26351.96,
      "status": "ativo"
    },
    {
      "id": 156,
      "data_aplicacao": "13/09/2024",
      "corretora": "AVENUE",
      "titulo": "MOVIDA - USD +8,96% - ABR/2029",
      "emissor": "MOVIDA",
      "taxa": "USD +8,96%",
      "vencimento": "11/04/2029",
      "classe": "RENDA FIXA",
      "tipo": "BONDS",
      "ticker": "",
      "moeda": "BRL",
      "custo_brl": "",
      "atual_brl": 25785.25,
      "status": "ativo"
    },
    {
      "id": 157,
      "data_aplicacao": "13/09/2024",
      "corretora": "AVENUE",
      "titulo": "FS BIO - USD +8,17% - FEV/2031",
      "emissor": "FS BIO",
      "taxa": "USD +8,17%",
      "vencimento": "12/02/2031",
      "classe": "RENDA FIXA",
      "tipo": "BONDS",
      "ticker": "",
      "moeda": "BRL",
      "custo_brl": "",
      "atual_brl": 26893.37,
      "status": "ativo"
    },
    {
      "id": 158,
      "data_aplicacao": "23/10/2024",
      "corretora": "AVENUE",
      "titulo": "3R PETROLEO - USD +8,31% - FEV/2031",
      "emissor": "3R",
      "taxa": "USD +8,31%",
      "vencimento": "05/02/2031",
      "classe": "RENDA FIXA",
      "tipo": "BONDS",
      "ticker": "",
      "moeda": "BRL",
      "custo_brl": "",
      "atual_brl": 27480.32,
      "status": "ativo"
    },
    {
      "id": 159,
      "data_aplicacao": "23/10/2024",
      "corretora": "AVENUE",
      "titulo": "SIMPAR - USD +8,34% - JAN/2031",
      "emissor": "SIMPAR",
      "taxa": "USD +8,34%",
      "vencimento": "26/01/2031",
      "classe": "RENDA FIXA",
      "tipo": "BONDS",
      "ticker": "",
      "moeda": "BRL",
      "custo_brl": "",
      "atual_brl": 22212.96,
      "status": "ativo"
    },
    {
      "id": 160,
      "data_aplicacao": "08/04/2025",
      "corretora": "AVENUE",
      "titulo": "AEGEA SANEAMENTO - USD +9% - JAN/2031",
      "emissor": "AEGEA",
      "taxa": "USD +9%",
      "vencimento": "20/01/2031",
      "classe": "RENDA FIXA",
      "tipo": "BONDS",
      "ticker": "",
      "moeda": "BRL",
      "custo_brl": "",
      "atual_brl": 25086.98,
      "status": "ativo"
    },
    {
      "id": 161,
      "data_aplicacao": "",
      "corretora": "Banco Inter",
      "titulo": "FII TRXF11",
      "emissor": "INTER",
      "taxa": "",
      "vencimento": "",
      "classe": "RENDA VARIÁVEL",
      "tipo": "FII",
      "ticker": "TRXF11",
      "moeda": "BRL",
      "custo_brl": 40438.69,
      "atual_brl": 38010.0,
      "status": "ativo"
    },
    {
      "id": 162,
      "data_aplicacao": "",
      "corretora": "Banco Inter",
      "titulo": "FII KDIF11",
      "emissor": "INTER",
      "taxa": "",
      "vencimento": "",
      "classe": "RENDA VARIÁVEL",
      "tipo": "FII",
      "ticker": "KDIF11",
      "moeda": "BRL",
      "custo_brl": 38730.69,
      "atual_brl": 37338.0,
      "status": "ativo"
    },
    {
      "id": 163,
      "data_aplicacao": "",
      "corretora": "BTG",
      "titulo": "FII BODB11",
      "emissor": "BTG",
      "taxa": "",
      "vencimento": "",
      "classe": "RENDA VARIÁVEL",
      "tipo": "FII",
      "ticker": "BODB11",
      "moeda": "BRL",
      "custo_brl": 15060.0,
      "atual_brl": 15640.0,
      "status": "ativo"
    },
    {
      "id": 164,
      "data_aplicacao": "",
      "corretora": "BTG",
      "titulo": "FII TGAR11",
      "emissor": "BTG",
      "taxa": "",
      "vencimento": "",
      "classe": "RENDA VARIÁVEL",
      "tipo": "FII",
      "ticker": "TGAR11",
      "moeda": "BRL",
      "custo_brl": 15015.0,
      "atual_brl": 10858.75,
      "status": "ativo"
    },
    {
      "id": 165,
      "data_aplicacao": "",
      "corretora": "BTG",
      "titulo": "FII BPML11",
      "emissor": "BTG",
      "taxa": "",
      "vencimento": "",
      "classe": "RENDA VARIÁVEL",
      "tipo": "FII",
      "ticker": "BPML11",
      "moeda": "BRL",
      "custo_brl": 40836.95,
      "atual_brl": 37411.57,
      "status": "ativo"
    },
    {
      "id": 166,
      "data_aplicacao": "",
      "corretora": "BTG",
      "titulo": "FII TRBL11",
      "emissor": "BTG",
      "taxa": "",
      "vencimento": "",
      "classe": "RENDA VARIÁVEL",
      "tipo": "FII",
      "ticker": "TRBL11",
      "moeda": "BRL",
      "custo_brl": 19508.98,
      "atual_brl": 16170.0,
      "status": "ativo"
    },
    {
      "id": 167,
      "data_aplicacao": "",
      "corretora": "BTG",
      "titulo": "SUZANO - SUZB3",
      "emissor": "SUZB3",
      "taxa": "",
      "vencimento": "",
      "classe": "RENDA VARIÁVEL",
      "tipo": "RV LOCAL",
      "ticker": "SUZB3",
      "moeda": "BRL",
      "custo_brl": 66289.02,
      "atual_brl": 57470.0,
      "status": "ativo"
    },
    {
      "id": 168,
      "data_aplicacao": "",
      "corretora": "BTG",
      "titulo": "KLABIN - KLBN11",
      "emissor": "KLBN11",
      "taxa": "",
      "vencimento": "",
      "classe": "RENDA VARIÁVEL",
      "tipo": "RV LOCAL",
      "ticker": "KLBN11",
      "moeda": "BRL",
      "custo_brl": 10395.0,
      "atual_brl": 10584.0,
      "status": "ativo"
    },
    {
      "id": 169,
      "data_aplicacao": "",
      "corretora": "Banco Inter",
      "titulo": "MÉLIUZ - CASH3",
      "emissor": "CASH3",
      "taxa": "",
      "vencimento": "",
      "classe": "RENDA VARIÁVEL",
      "tipo": "RV LOCAL",
      "ticker": "CASH3",
      "moeda": "BRL",
      "custo_brl": 18928.0,
      "atual_brl": 16728.0,
      "status": "ativo"
    },
    {
      "id": 170,
      "data_aplicacao": "",
      "corretora": "Banco Inter",
      "titulo": "WEG - WEGE3",
      "emissor": "WEGE3",
      "taxa": "",
      "vencimento": "",
      "classe": "RENDA VARIÁVEL",
      "tipo": "RV LOCAL",
      "ticker": "WEGE3",
      "moeda": "BRL",
      "custo_brl": 11920.2,
      "atual_brl": 8260.0,
      "status": "ativo"
    },
    {
      "id": 171,
      "data_aplicacao": "",
      "corretora": "Banco Inter",
      "titulo": "COSAN - CSAN3",
      "emissor": "CSAN3",
      "taxa": "",
      "vencimento": "",
      "classe": "RENDA VARIÁVEL",
      "tipo": "RV LOCAL",
      "ticker": "CSAN3",
      "moeda": "BRL",
      "custo_brl": 59122.77,
      "atual_brl": 63626.8,
      "status": "ativo"
    },
    {
      "id": 172,
      "data_aplicacao": "",
      "corretora": "Banco Inter",
      "titulo": "CMIN - CMIN3",
      "emissor": "CMIN3",
      "taxa": "",
      "vencimento": "",
      "classe": "RENDA VARIÁVEL",
      "tipo": "RV LOCAL",
      "ticker": "CMIN3",
      "moeda": "BRL",
      "custo_brl": 19929.1,
      "atual_brl": 15504.0,
      "status": "ativo"
    },
    {
      "id": 173,
      "data_aplicacao": "",
      "corretora": "Banco Inter",
      "titulo": "M DIAS BRANCO - MDIA3",
      "emissor": "MDIA3",
      "taxa": "",
      "vencimento": "",
      "classe": "RENDA VARIÁVEL",
      "tipo": "RV LOCAL",
      "ticker": "MDIA3",
      "moeda": "BRL",
      "custo_brl": 18372.64,
      "atual_brl": 15528.0,
      "status": "ativo"
    },
    {
      "id": 174,
      "data_aplicacao": "",
      "corretora": "Banco Inter",
      "titulo": "DIRECIONAL - DIRR3",
      "emissor": "DIRR3",
      "taxa": "",
      "vencimento": "",
      "classe": "RENDA VARIÁVEL",
      "tipo": "RV LOCAL",
      "ticker": "DIRR3",
      "moeda": "BRL",
      "custo_brl": 19964.0,
      "atual_brl": 17472.0,
      "status": "ativo"
    },
    {
      "id": 175,
      "data_aplicacao": "",
      "corretora": "Banco Inter",
      "titulo": "PLANO E PLANO - PLPL3",
      "emissor": "PLPL3",
      "taxa": "",
      "vencimento": "",
      "classe": "RENDA VARIÁVEL",
      "tipo": "RV LOCAL",
      "ticker": "PLPL3",
      "moeda": "BRL",
      "custo_brl": 17629.0,
      "atual_brl": 17323.0,
      "status": "ativo"
    },
    {
      "id": 176,
      "data_aplicacao": "12/08/2022",
      "corretora": "BTG",
      "titulo": "ABSOLUTE PACE LONG BIASED FIC FIA",
      "emissor": "ABSOLUTE",
      "taxa": "",
      "vencimento": "",
      "classe": "RENDA VARIÁVEL",
      "tipo": "RV LOCAL",
      "ticker": "",
      "moeda": "BRL",
      "custo_brl": 60000.0,
      "atual_brl": 98297.0,
      "status": "ativo"
    },
    {
      "id": 177,
      "data_aplicacao": "12/08/2022",
      "corretora": "BTG",
      "titulo": "OCEANA LONG BIASED FIC FIA (PGBL)",
      "emissor": "OCEANA",
      "taxa": "",
      "vencimento": "",
      "classe": "RENDA VARIÁVEL",
      "tipo": "RV LOCAL",
      "ticker": "",
      "moeda": "BRL",
      "custo_brl": 80000.0,
      "atual_brl": 114641.0,
      "status": "ativo"
    },
    {
      "id": 178,
      "data_aplicacao": "13/06/2025",
      "corretora": "XP",
      "titulo": "ARX DENALI XP SEG PREV FIC FIRF CP RL",
      "emissor": "XP VIDA E PREVIDENCIA",
      "taxa": "",
      "vencimento": "",
      "classe": "RENDA FIXA",
      "tipo": "RV LOCAL",
      "ticker": "",
      "moeda": "BRL",
      "custo_brl": 111500.0,
      "atual_brl": 123859.0,
      "status": "ativo"
    },
    {
      "id": 179,
      "data_aplicacao": "14/08/2024",
      "corretora": "BTG",
      "titulo": "ABSOLUTE ATENAS PREV FIRF CRPR ACCESS (VGBL)",
      "emissor": "ABSOLUTE",
      "taxa": "",
      "vencimento": "",
      "classe": "RENDA FIXA",
      "tipo": "RV LOCAL",
      "ticker": "",
      "moeda": "BRL",
      "custo_brl": 20000.0,
      "atual_brl": 29596.0,
      "status": "ativo"
    },
    {
      "id": 180,
      "data_aplicacao": "09/09/2021",
      "corretora": "BTG",
      "titulo": "ICATU VANGUARDA ABSOLUTO II FI RF CP (PGBL 285290)",
      "emissor": "ICATU VANGUARDA",
      "taxa": "",
      "vencimento": "",
      "classe": "RENDA FIXA",
      "tipo": "CREDITO PRIVADO",
      "ticker": "",
      "moeda": "BRL",
      "custo_brl": 41859.0,
      "atual_brl": 46099.0,
      "status": "ativo"
    },
    {
      "id": 181,
      "data_aplicacao": "",
      "corretora": "BTG",
      "titulo": "ICATU VANGUARDA ABSOLUTO II FI RF CP (VGBL 198487)",
      "emissor": "ICATU VANGUARDA",
      "taxa": "",
      "vencimento": "",
      "classe": "RENDA FIXA",
      "tipo": "CREDITO PRIVADO",
      "ticker": "",
      "moeda": "BRL",
      "custo_brl": 50000.0,
      "atual_brl": 59300.0,
      "status": "ativo"
    },
    {
      "id": 182,
      "data_aplicacao": "",
      "corretora": "BTG",
      "titulo": "ICATU VANGUARDA ABSOLUTO II FI RF CP (PGBL 108795)",
      "emissor": "ICATU VANGUARDA",
      "taxa": "",
      "vencimento": "",
      "classe": "RENDA FIXA",
      "tipo": "CREDITO PRIVADO",
      "ticker": "",
      "moeda": "BRL",
      "custo_brl": 65340.0,
      "atual_brl": 63553.0,
      "status": "ativo"
    },
    {
      "id": 183,
      "data_aplicacao": "",
      "corretora": "BTG",
      "titulo": "ABSOLUTE ATENAS PREV FIRF CRPR ACCESS (PGBL 285290)",
      "emissor": "ABSOLUTE",
      "taxa": "",
      "vencimento": "",
      "classe": "RENDA FIXA",
      "tipo": "MM",
      "ticker": "",
      "moeda": "BRL",
      "custo_brl": 126810.0,
      "atual_brl": 172592.0,
      "status": "ativo"
    },
    {
      "id": 184,
      "data_aplicacao": "31/10/2024",
      "corretora": "BTG",
      "titulo": "BTG CRED CORP II PREV FICFIM CrPr (PGBL 285290)",
      "emissor": "BTG",
      "taxa": "",
      "vencimento": "",
      "classe": "RENDA FIXA",
      "tipo": "MM",
      "ticker": "",
      "moeda": "BRL",
      "custo_brl": 145249.0,
      "atual_brl": 206698.0,
      "status": "ativo"
    },
    {
      "id": 185,
      "data_aplicacao": "",
      "corretora": "AVENUE",
      "titulo": "ETF IWDA",
      "emissor": "IWDA",
      "taxa": "",
      "vencimento": "",
      "classe": "RENDA VARIÁVEL",
      "tipo": "INTERNACIONAL",
      "ticker": "IWDA",
      "moeda": "USD",
      "custo_brl": 46530.33,
      "atual_brl": 49402.84,
      "status": "ativo"
    },
    {
      "id": 186,
      "data_aplicacao": "",
      "corretora": "AVENUE",
      "titulo": "ETF USSC",
      "emissor": "USSC",
      "taxa": "",
      "vencimento": "",
      "classe": "RENDA VARIÁVEL",
      "tipo": "INTERNACIONAL",
      "ticker": "USSC",
      "moeda": "USD",
      "custo_brl": 36623.48,
      "atual_brl": 51518.08,
      "status": "ativo"
    },
    {
      "id": 187,
      "data_aplicacao": "",
      "corretora": "AVENUE",
      "titulo": "ETF EIMI",
      "emissor": "EIMI",
      "taxa": "",
      "vencimento": "",
      "classe": "RENDA VARIÁVEL",
      "tipo": "INTERNACIONAL",
      "ticker": "EIMI",
      "moeda": "USD",
      "custo_brl": 15095.08,
      "atual_brl": 25889.38,
      "status": "ativo"
    },
    {
      "id": 188,
      "data_aplicacao": "",
      "corretora": "IB",
      "titulo": "ETF IBIT",
      "emissor": "IBIT",
      "taxa": "",
      "vencimento": "",
      "classe": "RENDA VARIÁVEL",
      "tipo": "INTERNACIONAL",
      "ticker": "IBIT",
      "moeda": "USD",
      "custo_brl": 49299.9,
      "atual_brl": 52825.36,
      "status": "ativo"
    },
    {
      "id": 189,
      "data_aplicacao": "",
      "corretora": "IB",
      "titulo": "ETF BORR",
      "emissor": "BORR",
      "taxa": "",
      "vencimento": "",
      "classe": "RENDA VARIÁVEL",
      "tipo": "INTERNACIONAL",
      "ticker": "BORR",
      "moeda": "USD",
      "custo_brl": 58324.66,
      "atual_brl": 84156.26,
      "status": "ativo"
    },
    {
      "id": 190,
      "data_aplicacao": "",
      "corretora": "IB",
      "titulo": "PAYPAL - PYPL",
      "emissor": "PYPL",
      "taxa": "",
      "vencimento": "",
      "classe": "RENDA VARIÁVEL",
      "tipo": "INTERNACIONAL",
      "ticker": "PYPL",
      "moeda": "USD",
      "custo_brl": 64473.2,
      "atual_brl": 66532.63,
      "status": "ativo"
    },
    {
      "id": 191,
      "data_aplicacao": "",
      "corretora": "IB",
      "titulo": "VZLA",
      "emissor": "VZLA",
      "taxa": "",
      "vencimento": "",
      "classe": "RENDA VARIÁVEL",
      "tipo": "INTERNACIONAL",
      "ticker": "VZLA",
      "moeda": "USD",
      "custo_brl": 30017.86,
      "atual_brl": 28866.73,
      "status": "ativo"
    },
    {
      "id": 192,
      "data_aplicacao": "",
      "corretora": "AVENUE",
      "titulo": "ASX:CSL",
      "emissor": "ASX:CSL",
      "taxa": "",
      "vencimento": "",
      "classe": "RENDA VARIÁVEL",
      "tipo": "INTERNACIONAL",
      "ticker": "ASX:CSL",
      "moeda": "USD",
      "custo_brl": 57477.6,
      "atual_brl": 50811.01,
      "status": "ativo"
    },
    {
      "id": 193,
      "data_aplicacao": "",
      "corretora": "Banco Inter",
      "titulo": "DOW INC - DOW",
      "emissor": "DOW",
      "taxa": "",
      "vencimento": "",
      "classe": "RENDA VARIÁVEL",
      "tipo": "INTERNACIONAL",
      "ticker": "DOW",
      "moeda": "USD",
      "custo_brl": 28841.43,
      "atual_brl": 28644.09,
      "status": "ativo"
    },
    {
      "id": 194,
      "data_aplicacao": "",
      "corretora": "AVENUE",
      "titulo": "ASX:COH",
      "emissor": "ASX:COH",
      "taxa": "",
      "vencimento": "",
      "classe": "RENDA VARIÁVEL",
      "tipo": "INTERNACIONAL",
      "ticker": "ASX:COH",
      "moeda": "USD",
      "custo_brl": 24715.08,
      "atual_brl": 24024.41,
      "status": "ativo"
    },
    {
      "id": 195,
      "data_aplicacao": "",
      "corretora": "AVENUE",
      "titulo": "GDXJ",
      "emissor": "GDXJ",
      "taxa": "",
      "vencimento": "",
      "classe": "RENDA VARIÁVEL",
      "tipo": "INTERNACIONAL",
      "ticker": "GDXJ",
      "moeda": "USD",
      "custo_brl": 28807.76,
      "atual_brl": 25114.81,
      "status": "ativo"
    },
    {
      "id": 196,
      "data_aplicacao": "",
      "corretora": "AVENUE",
      "titulo": "NOM",
      "emissor": "NOM",
      "taxa": "",
      "vencimento": "",
      "classe": "RENDA VARIÁVEL",
      "tipo": "INTERNACIONAL",
      "ticker": "NOM",
      "moeda": "USD",
      "custo_brl": 2089.74,
      "atual_brl": 1753.26,
      "status": "ativo"
    },
    {
      "id": 197,
      "data_aplicacao": "",
      "corretora": "AVENUE",
      "titulo": "ASX:TPW",
      "emissor": "ASX:TPW",
      "taxa": "",
      "vencimento": "",
      "classe": "RENDA VARIÁVEL",
      "tipo": "INTERNACIONAL",
      "ticker": "ASX:TPW",
      "moeda": "USD",
      "custo_brl": 35419.3,
      "atual_brl": 35773.49,
      "status": "ativo"
    },
    {
      "id": 198,
      "data_aplicacao": "",
      "corretora": "AVENUE",
      "titulo": "ASX:DXS",
      "emissor": "ASX:DXS",
      "taxa": "",
      "vencimento": "",
      "classe": "RENDA VARIÁVEL",
      "tipo": "INTERNACIONAL",
      "ticker": "ASX:DXS",
      "moeda": "USD",
      "custo_brl": 32098.9,
      "atual_brl": 32770.95,
      "status": "ativo"
    },
    {
      "id": 199,
      "data_aplicacao": "",
      "corretora": "AVENUE",
      "titulo": "ETF VT - VANGUARD TOTAL WORLD",
      "emissor": "VT",
      "taxa": "",
      "vencimento": "",
      "classe": "RENDA VARIÁVEL",
      "tipo": "ALTERNATIVO",
      "ticker": "VT",
      "moeda": "USD",
      "custo_brl": 260824.14,
      "atual_brl": 288939.05,
      "status": "ativo"
    },
    {
      "id": 200,
      "data_aplicacao": "",
      "corretora": "IB",
      "titulo": "MICROSTRATEGY - MSTR",
      "emissor": "MSTR",
      "taxa": "",
      "vencimento": "",
      "classe": "RENDA VARIÁVEL",
      "tipo": "ALTERNATIVO",
      "ticker": "MSTR",
      "moeda": "USD",
      "custo_brl": 63479.02,
      "atual_brl": 71638.97,
      "status": "ativo"
    },
    {
      "id": 201,
      "data_aplicacao": "",
      "corretora": "IB",
      "titulo": "ASX:LLC (ALTERNATIVO)",
      "emissor": "ASX:LLC",
      "taxa": "",
      "vencimento": "",
      "classe": "RENDA VARIÁVEL",
      "tipo": "ALTERNATIVO",
      "ticker": "ASX:LLC",
      "moeda": "USD",
      "custo_brl": 51946.84,
      "atual_brl": 49714.53,
      "status": "ativo"
    },
    {
      "id": 202,
      "data_aplicacao": "",
      "corretora": "AVENUE",
      "titulo": "FNV - FRANCO-NEVADA",
      "emissor": "FNV",
      "taxa": "",
      "vencimento": "",
      "classe": "RENDA VARIÁVEL",
      "tipo": "ALTERNATIVO",
      "ticker": "FNV",
      "moeda": "USD",
      "custo_brl": 29079.25,
      "atual_brl": 28176.05,
      "status": "ativo"
    },
    {
      "id": 203,
      "data_aplicacao": "",
      "corretora": "Banco Inter",
      "titulo": "BITH11 - BITCOIN ETF",
      "emissor": "BITH11",
      "taxa": "",
      "vencimento": "",
      "classe": "RENDA VARIÁVEL",
      "tipo": "ALTERNATIVO",
      "ticker": "BITH11",
      "moeda": "BRL",
      "custo_brl": 14544.0,
      "atual_brl": 12880.0,
      "status": "ativo"
    },
    {
      "id": 204,
      "data_aplicacao": "",
      "corretora": "BTG",
      "titulo": "AURA33 - AURA MINERALS",
      "emissor": "AURA33",
      "taxa": "",
      "vencimento": "",
      "classe": "RENDA VARIÁVEL",
      "tipo": "ALTERNATIVO",
      "ticker": "AURA33",
      "moeda": "BRL",
      "custo_brl": 15375.5,
      "atual_brl": 13771.25,
      "status": "ativo"
    },
    {
      "id": 205,
      "data_aplicacao": "",
      "corretora": "Wallet",
      "titulo": "BTC / CRIPTOATIVOS WALLET",
      "emissor": "BTC",
      "taxa": "",
      "vencimento": "",
      "classe": "RENDA VARIÁVEL",
      "tipo": "ALTERNATIVO",
      "ticker": "BTC",
      "moeda": "USD",
      "custo_brl": 63479.02,
      "atual_brl": 111507.13,
      "status": "ativo"
    }
  ]
}